Workbook

Sheet Стоимость производства
A1: Оценка себестоимости производства зубной пасты (Oral-B Pro-Clinic Check&Restore)
A3: Ингредиент | B3: % в составе | C3: Цена за кг (руб, опт 2025) | D3: Один продукт ( 75 мл ) (руб) | F3: Стоимость производства одного тюбика 75 мл
A4: Aqua (вода) | B4: =37.4 -> 37.4 | C4: 2.5 | D4: =(C4/13.33)*(B4/100) -> 0.070142536 | F4: Название | G4: В % от издержек | H4: Стоимость (руб)
A5: Sorbitol | B5: 29.36 | C5: 226 | D5: =(C5/13.33)*(B5/100) -> 4.9777644 | F5: Сырье и материалы | G5: =H5/$H$12 -> 0.4690676 | H5: =D19 -> 54.726692
A6: Glycerin / увлажнитель | B6: 2.936 | C6: 135 | D6: =(C6/13.33)*(B6/100) -> 0.29734434 | F6: Производственные затраты | G6: =H6/$H$12 -> 0.25456148 | H6: 29.7
A7: Hydrated Silica (абразив) | B7: 11.747 | C7: 530 | D7: =(C7/13.33)*(B7/100) -> 4.6706002 | F7: Логистика и складирование | G7: =H7/$H$12 -> 0.075425624 | H7: 8.8
A8: Nano-Hydroxyapatite | B8: 6.853 | C8: 5150 | D8: =(C8/13.33)*(B8/100) -> 26.476332 | F8: Экологическая премиальная упаковка | G8: =H8/$H$12 -> 0.088282265 | H8: 10.3
A9: Stannous fluoride (актив фторид) | B9: 0.441 | C9: 4800 | D9: =(C9/13.33)*(B9/100) -> 1.587997 | F9: Производственные потери ( брак ) | G9: =H9/$H$12 -> 0.009381352 | H9: =H5*0.02 -> 1.0945338
A10: Potassium nitrate | B10: 0.98 | C10: 4780 | D10: =(C10/13.33)*(B10/100) -> 3.5141785 | F10: Тестирование | G10: =H10/$H$12 -> 0.019456383 | H10: 2.27
A11: Zinc citrate | B11: 0.49 | C11: 430 | D11: =(C11/13.33)*(B11/100) -> 0.15806452 | F11: 2 таблетки-индикаторы | G11: =H11/$H$12 -> 0.083825296 | H11: =H21*2 -> 9.78
A12: Xylitol | B12: 2.94 | C12: 850 | D12: =(C12/13.33)*(B12/100) -> 1.8747187 | F12: Итог | G12: =SUM(G5:G11) -> 1 | H12: =SUM(H5:H11)*CHOOSE(Scenarios!B8,Scenarios!B6,Scenarios!C6,Scenarios!D6) -> 116.67123
A13: Экстракт гуараны | B13: 0.49 | C13: 8000 | D13: =(C13/13.33)*(B13/100) -> 2.9407352
A14: Ароматизаторы | B14: 1.25 | C14: 785 | D14: =(C14/13.33)*(B14/100) -> 0.73612153 | F14: Стоимость производства двух таблеток-индикаторов
A15: ПАВы | B15: 1.5 | C15: 2980 | D15: =(C15/13.33)*(B15/100) -> 3.3533383 | F15: Компонент | G15: % в таблетке | H15: Одна таблетка (руб)
A16: Cl | B16: 0.25 | C16: 85 | D16: =(C16/13.33)*(B16/100) -> 0.015941485 | F16: Кальций карбонат (абразив, мягкий контроль) | G16: 0.4 | H16: 0.97
A17: Консерванты | B17: 0.8 | C17: 290 | D17: =(C17/13.33)*(B17/100) -> 0.17404351 | F17: Фторид натрия / стронний фторид | G17: 0.2 | H17: 0.93
A18: Доп загустители | B18: 2.56 | C18: 2020 | D18: =(C18/13.33)*(B18/100) -> 3.8793698 | F18: Пищевой краситель для индикатора | G18: 0.15 | H18: 0.51
A19: Итог | B19: =SUM(B4:B18) -> 99.997 | D19: =SUM(D4:D18) -> 54.726692 | F19: Экстракт гуараны / натуральный аромат | G19: 0.1 | H19: 0.48
F20: Связующие и стабилизаторы | G20: 0.15 | H20: 2
F21: Итого | G21: 1 | H21: =SUM(H16:H20) -> 4.89
A24: Оценка себестоимости производства зубной пасты (Oral-B Pro-Clinic Sensitive Shield)
A26: Ингредиент | B26: % в составе | C26: Цена за кг (руб, опт 2025) | D26: Один продукт ( 75 мл ) (руб) | F26: Стоимость производства одного тюбика 75 мл
A27: Aqua (вода) | B27: 34.48 | C27: 2.5 | D27: =(C27/13.33)*(B27/100) -> 0.064666167 | F27: Название | G27: В % от издержек | H27: Стоимость (руб)
A28: Sorbitol | B28: 29.97 | C28: 226 | D28: =(C28/13.33)*(B28/100) -> 5.0811853 | F28: Сырье и материалы | G28: =H28/$H$34 -> 0.55070545 | H28: =D42 -> 64.705304
A29: Glycerin / увлажнитель | B29: 2.99 | C29: 135 | D29: =(C29/13.33)*(B29/100) -> 0.3028132 | F29: Производственные затраты | G29: =H29/$H$34 -> 0.25447826 | H29: 29.9
A30: Hydrated Silica | B30: 10.53 | C30: 530 | D30: =(C30/13.33)*(B30/100) -> 4.1867217 | F30: Логистика и складирование | G30: =H30/$H$34 -> 0.075747708 | H30: 8.9
A31: Potassium Nitrate | B31: 4.98 | C31: 5150 | D31: =(C31/13.33)*(B31/100) -> 19.24006 | F31: Экологическая премиальная упаковка | G31: =H31/$H$34 -> 0.088514176 | H31: 10.4
A32: Nano-Hydroxyapatite | B32: 5.51 | C32: 4800 | D32: =(C32/13.33)*(B32/100) -> 19.84096 | F32: Производственные потери ( брак ) | G32: =H32/$H$34 -> 0.011404711 | H32: 1.34
A33: Stannous fluoride | B33: 0.41 | C33: 4780 | D33: =(C33/13.33)*(B33/100) -> 1.4702176 | F33: Тестирование | G33: =H33/$H$34 -> 0.019149702 | H33: 2.25
A34: Zinc citrate | B34: 0.49 | C34: 430 | D34: =(C34/13.33)*(B34/100) -> 0.15806452 | F34: Итог | G34: =SUM(G27:G33) -> 1 | H34: =SUM(H27:H33)*CHOOSE(Scenarios!B8,Scenarios!B6,Scenarios!C6,Scenarios!D6) -> 117.4953
A35: Xylitol | B35: 2.22 | C35: 850 | D35: =(C35/13.33)*(B35/100) -> 1.4156039
A36: Ароматизаторы | B36: 1.23 | C36: 8000 | D36: =(C36/13.33)*(B36/100) -> 7.3818455
A37: ПАВы | B37: 1.47 | C37: 785 | D37: =(C37/13.33)*(B37/100) -> 0.86567892
A38: Cl | B38: 0.26 | C38: 2980 | D38: =(C38/13.33)*(B38/100) -> 0.58124531
A39: Консерванты | B39: 0.79 | C39: 85 | D39: =(C39/13.33)*(B39/100) -> 0.050375094
A40: Доп загустители | B40: 2.32 | C40: 290 | D40: =(C40/13.33)*(B40/100) -> 0.50472618
A41: Дополнительные загустители (кроскармеллоза, ксантан) | B41: 2.35 | C41: 2020 | D41: =(C41/13.33)*(B41/100) -> 3.5611403
A42: Итог | B42: =SUM(B27:B41) -> 100 | D42: =SUM(D27:D41) -> 64.705304
A50: Оценка себестоимости производства зубной пасты (Oral-B Pro-Clinic Caries Defense)
A52: Ингредиент | B52: % в составе | C52: Цена за кг (руб, опт 2025) | D52: Один продукт ( 75 мл ) (руб) | F52: Стоимость производства одного тюбика 75 мл
A53: Aqua (вода) | B53: 38.75 | C53: 2.5 | D53: =(C53/13.33)*(B53/100) -> 0.072674419 | F53: Название | G53: В % от издержек | H53: Стоимость (руб)
A54: Sorbitol | B54: 29.9 | C54: 226 | D54: =(C54/13.33)*(B54/100) -> 5.0693173 | F54: Сырье и материалы | G54: =H54/$H$61 -> 0.47245527 | H54: =D67 -> 46.623575
A55: Glycerin / увлажнитель | B55: 2.95 | C55: 135 | D55: =(C55/13.33)*(B55/100) -> 0.29876219 | F55: Производственные затраты | G55: =H55/$H$61 -> 0.30227928 | H55: 29.83
A56: Hydrated Silica | B56: 11 | C56: 530 | D56: =(C56/13.33)*(B56/100) -> 4.3735934 | F56: Логистика и складирование | G56: =H56/$H$61 -> 0.088768572 | H56: 8.76
A57: Nano-Hydroxyapatite | B57: 6 | C57: 4800 | D57: =(C57/13.33)*(B57/100) -> 21.605401 | F57: Экологическая премиальная упаковка | G57: =H57/$H$61 -> 0.10457667 | H57: 10.32
A58: Sodium Fluoride | B58: 0.5 | C58: 6000 | D58: =(C58/13.33)*(B58/100) -> 2.2505626 | F58: Производственные потери ( брак ) | G58: =H58/$H$61 -> 0.0095253947 | H58: 0.94
A59: Stannous fluoride | B59: 0.45 | C59: 4780 | D59: =(C59/13.33)*(B59/100) -> 1.6136534 | F59: Тестирование | G59: =H59/$H$61 -> 0.022394811 | H59: 2.21
A60: Zinc citrate | B60: 0.55 | C60: 430 | D60: =(C60/13.33)*(B60/100) -> 0.17741935
A61: Xylitol | B61: 3 | C61: 850 | D61: =(C61/13.33)*(B61/100) -> 1.9129782 | F61: Итог | G61: =SUM(G54:G60) -> 1 | H61: =SUM(H54:H60)*CHOOSE(Scenarios!B8,Scenarios!B6,Scenarios!C6,Scenarios!D6) -> 98.683575
A62: Ароматизаторы | B62: 1.15 | C62: 8000 | D62: =(C62/13.33)*(B62/100) -> 6.9017254
A63: ПАВы | B63: 1.98 | C63: 785 | D63: =(C63/13.33)*(B63/100) -> 1.1660165
A64: Cl | B64: 0.24 | C64: 2980 | D64: =(C64/13.33)*(B64/100) -> 0.53653413
A65: Консерванты | B65: 0.8 | C65: 85 | D65: =(C65/13.33)*(B65/100) -> 0.051012753
A66: Доп загустители | B66: 2.73 | C66: 290 | D66: =(C66/13.33)*(B66/100) -> 0.59392348
A67: Итог | B67: =SUM(B52:B66) -> 100 | D67: =SUM(D52:D66) -> 46.623575

Sheet Scenarios
A1: Параметр | B1: Негатив (1) | C1: Базовый (2) | D1: Оптимистичный (3)
A2: Множитель объёма (2027-2028) | B2: 0.9 | C2: 1 | D2: 1.1
A3: Множитель объёма (2029-2031) | B3: 0.9 | C3: 1 | D3: 1
A4: Изменение CAPEX | B4: 1.1 | C4: 1 | D4: 0.9
A5: Изменение WACC | B5: 0.02 | C5: 0 | D5: -0.03
A6: Изменение себестоимости | B6: 1.1 | C6: 1 | D6: 0.9
A7: Изменение OPEX | B7: 1.075 | C7: 1 | D7: 0.9
A8: Выбранный сценарий | B8: 2 | C8: (можно поменять сценарий, изменив поле B8)

Sheet Assumptions
A2: Макроэкономические показатели
A3: Ключевая ставка | B3: 0.155
A4: Рост ВВП ( прогноз ) | B4: 0.012
A5: Индекс потребительских цен | B5: 0.0581
A7: Параметры рынка и финансовой модели
A8: Объем рынка (млн. руб) | B8: 57000
A9: Средняя стоимость зубной пасты (руб) | B9: 232
A10: Налог на прибыль | B10: 0.25
A11: Доля сегмента Spec.Health | B11: =17.8/100 -> 0.178
A12: Объем рынка Spec.Health (млн. руб) | B12: =B11*B8 -> 10146
A13: Цикл покупки | B13: 3 месяца
A14: Горизонт модели | B14: 5 лет
A15: Премия за риск | B15: 0.05
A17: Целевой объем выпуска | F17: Продукция Oral-B Pro-Clinic
F18: Название | G18: % от выпуска (целевой) | H18: Описание | M18: Цена отгрузки (2027, руб) | N18: Цена полки (2027, руб) | O18: Цена отгрузки (2028-2029, руб) | P18: Цена полки (2028-2029, руб) | Q18: Цена отгрузки (2030-2031, руб) | R18: Цена полки (2030-2031, руб)
F19: Oral-B Pro-Clinic Check&Restore | G19: 60 | H19: Комплексное восстановление и защита «всё в одном» | M19: =N19/1.2 * 0.65 -> 265.41667 | N19: 490 | O19: =P19/1.2 * 0.65 -> 281.66667 | P19: 520 | Q19: =R19/1.2 * 0.65 -> 319.58333 | R19: 590
A20: Название | B20: Oral-B Pro-Clinic Total Restore | C20: Oral-B Pro-Clinic Sensitive Shield | D20: Oral-B Pro-Clinic Caries Defense | F20: Oral-B Pro-Clinic Sensitive Shield | G20: 25 | H20: Мгновенное и длительное облегчение повышенной чувствительности | M20: =N20/1.2 * 0.65 -> 238.33333 | N20: 440 | O20: =P20/1.2 * 0.65 -> 254.58333 | P20: 470 | Q20: =R20/1.2 * 0.65 -> 276.25 | R20: 510
A21: Объем выпуска тыс/мес | B21: =B24/12 -> 50 | C21: =C24/12 -> 20.833333 | D21: =D24/12 -> 12.5 | F21: Oral-B Pro-Clinic Caries Defense | G21: 15 | H21: Максимальная профилактика кариеса и укрепление эмали. | M21: =N21/1.2 * 0.65 -> 238.33333 | N21: 440 | O21: =P21/1.2 * 0.65 -> 243.75 | P21: 450 | Q21: =R21/1.2 * 0.65 -> 270.83333 | R21: 500
A24: Объем выпуска тыс/год | B24: =1000*G19/100 -> 600 | C24: =1000*G20/100 -> 250 | D24: =1000*G21/100 -> 150
A29: CAPEX | E29: OPEX | L29: Production Costs
A30: Название | B30: Цена (тыс. руб) | C30: Срок службы (лет) | E30: Продукт | F30: Стоимость в месяц (2027–2030) | G30: Стоимость в год (2031) | L30: Продукт | M30: Себестоимость
A31: Линия для производства зубной пасты с вакуумным эмульсификатором и высокосдвиговым гомогенизатором | B31: =1510*CHOOSE(Scenarios!B8,Scenarios!B4,Scenarios!C4,Scenarios!D4) -> 1510 | C31: 10 | E31: Заработная плата офисного персонала | F31: 500 | G31: 500 | L31: Oral-B Pro-Clinic Check&Restore | M31: ='Стоимость производства'!H12 -> 116.67123
A32: Линия наполнения тюбиков | B32: =3010*CHOOSE(Scenarios!B8,Scenarios!B4,Scenarios!C4,Scenarios!D4) -> 3010 | C32: 10 | E32: Маркетинг и продвижение ( стоматологических мероприятия, E-COM, выкуп полки в магазинах ) | F32: 1830 | G32: 1800 | L32: Oral-B Pro-Clinic Sensitive Shield | M32: ='Стоимость производства'!H34 -> 117.4953
A33: Автоматический этикетировщик | B33: =749*CHOOSE(Scenarios!B8,Scenarios!B4,Scenarios!C4,Scenarios!D4) -> 749 | C33: 7 | E33: Аренда и коммунальные услуги (офис + склады) | F33: 200 | G33: 200 | L33: Oral-B Pro-Clinic Caries Defense | M33: ='Стоимость производства'!H61 -> 98.683575
A34: Двухкамерный вакуумный упаковщик | B34: =293*CHOOSE(Scenarios!B8,Scenarios!B4,Scenarios!C4,Scenarios!D4) -> 293 | C34: 7 | E34: Логистика (от склада до клиента) | F34: 400 | G34: 400
A35: Компрессор безмасляный | B35: =312*CHOOSE(Scenarios!B8,Scenarios!B4,Scenarios!C4,Scenarios!D4) -> 312 | C35: 8 | E35: Обслуживание и ремонт оборудования | F35: 100 | G35: 100
A36: RO‑система (система водоподготовки) | B36: =3125*CHOOSE(Scenarios!B8,Scenarios!B4,Scenarios!C4,Scenarios!D4) -> 3125 | C36: 6 | E36: Страхование и лицензии | F36: 50 | G36: 50
A37: Монтаж, пусконаладка, обучение персонала | B37: =1050*CHOOSE(Scenarios!B8,Scenarios!B4,Scenarios!C4,Scenarios!D4) -> 1050 | C37: 5 | E37: Прочие расходы (канцелярия, IT, связь) | F37: 50 | G37: 50
A38: Помещение и склад | B38: =45000*CHOOSE(Scenarios!B8,Scenarios!B4,Scenarios!C4,Scenarios!D4) -> 45000 | C38: 20 | E38: Заработая плата медицинских представителей | F38: 1500 | G38: 1050
A39: Лаборатория + контроль качества | B39: =8000*CHOOSE(Scenarios!B8,Scenarios!B4,Scenarios!C4,Scenarios!D4) -> 8000 | C39: 10 | E39: Итог 2027-2029 (тыс. руб) | F39: =SUM(F31:F38)*CHOOSE(Scenarios!B8,Scenarios!B7,Scenarios!C7,Scenarios!D7) -> 4630
A40: Прочая инфраструктура | B40: =7000*CHOOSE(Scenarios!B8,Scenarios!B4,Scenarios!C4,Scenarios!D4) -> 7000 | C40: 20 | E40: Итог 2030-2031 (тыс. руб) | F40: =SUM(G31:G38)*CHOOSE(Scenarios!B8,Scenarios!B7,Scenarios!C7,Scenarios!D7) -> 4150
A41: Вакуумный миксер-гомогенизатор | B41: =15000*CHOOSE(Scenarios!B8,Scenarios!B4,Scenarios!C4,Scenarios!D4) -> 15000 | C41: 8
A42: Итог (тыс. руб) | B42: =SUM(B31:B41) -> 85049
A43: Амортизация (в месяц, тыс. руб) | B43: =(B31/C31+B32/C32+B33/C33+B34/C34+B35/C35+B36/C36+B37/C37+B38/C38+B39/C39+B40/C40 + B41/C41)/12 -> 553.80754

Sheet P&L
D7: Прогноз на 2027 год
F8: 46023 | G8: 46054 | H8: 46082 | I8: 46113 | J8: 46143 | K8: 46174 | L8: 46204 | M8: 46235 | N8: 46266 | O8: 46296 | P8: 46327 | Q8: 46357 | R8: Итог | U8: Год | V8: Общий объем продаж | W8: Общая выручка | X8: Чистая прибыль | Y8: ROS | Z8: Маржинальная прибыль | AA8: ROMI | AB8: ROI | AC8: BEP (2027) | AD8: Result (BEP)
D9: Объем продаж | E9: Oral-B Pro-Clinic Total Restore | F9: =12000*CHOOSE(Scenarios!$B$8,Scenarios!$B$2,Scenarios!$C$2,Scenarios!$D$2) -> 12000 | G9: =18000*CHOOSE(Scenarios!$B$8,Scenarios!$B$2,Scenarios!$C$2,Scenarios!$D$2) -> 18000 | H9: =24000*CHOOSE(Scenarios!$B$8,Scenarios!$B$2,Scenarios!$C$2,Scenarios!$D$2) -> 24000 | I9: =30000*CHOOSE(Scenarios!$B$8,Scenarios!$B$2,Scenarios!$C$2,Scenarios!$D$2) -> 30000 | J9: =33000*CHOOSE(Scenarios!$B$8,Scenarios!$B$2,Scenarios!$C$2,Scenarios!$D$2) -> 33000 | K9: =36000*CHOOSE(Scenarios!$B$8,Scenarios!$B$2,Scenarios!$C$2,Scenarios!$D$2) -> 36000 | L9: =36000*CHOOSE(Scenarios!$B$8,Scenarios!$B$2,Scenarios!$C$2,Scenarios!$D$2) -> 36000 | M9: =39000*CHOOSE(Scenarios!$B$8,Scenarios!$B$2,Scenarios!$C$2,Scenarios!$D$2) -> 39000 | N9: =39000*CHOOSE(Scenarios!$B$8,Scenarios!$B$2,Scenarios!$C$2,Scenarios!$D$2) -> 39000 | O9: =39000*CHOOSE(Scenarios!$B$8,Scenarios!$B$2,Scenarios!$C$2,Scenarios!$D$2) -> 39000 | P9: =42000*CHOOSE(Scenarios!$B$8,Scenarios!$B$2,Scenarios!$C$2,Scenarios!$D$2) -> 42000 | Q9: =42000*CHOOSE(Scenarios!$B$8,Scenarios!$B$2,Scenarios!$C$2,Scenarios!$D$2) -> 42000 | R9: =SUM(F9:Q9) -> 390000 | U9: 2027 | V9: =SUM(R9:R11) -> 650000 | W9: =SUM(R12:R14) -> 165479.17 | X9: =R27 -> 20955.946 | Y9: =X9/W9 -> 0.12663797 | Z9: =SUM(R22:R24) -> 91262.753 | AA9: =(SUM(Z9:Z11)-(R18*3)) / (R18*3) -> 4.5728313 | AB9: =(SUM(X9:X13)-Assumptions!B42)/(Assumptions!B42) -> 2.0806536 | AC9: =$R$20/(Assumptions!$M$19-'Стоимость производства'!$H$12) -> 373.52405 | AD9: =AC9*0.6+AC10*0.25+AC11*0.15 -> 398.73956
E10: Oral-B Pro-Clinic Sensitive Shield | F10: =5000*CHOOSE(Scenarios!$B$8,Scenarios!$B$2,Scenarios!$C$2,Scenarios!$D$2) -> 5000 | G10: =7500*CHOOSE(Scenarios!$B$8,Scenarios!$B$2,Scenarios!$C$2,Scenarios!$D$2) -> 7500 | H10: =10000*CHOOSE(Scenarios!$B$8,Scenarios!$B$2,Scenarios!$C$2,Scenarios!$D$2) -> 10000 | I10: =12500*CHOOSE(Scenarios!$B$8,Scenarios!$B$2,Scenarios!$C$2,Scenarios!$D$2) -> 12500 | J10: =13750*CHOOSE(Scenarios!$B$8,Scenarios!$B$2,Scenarios!$C$2,Scenarios!$D$2) -> 13750 | K10: =15000*CHOOSE(Scenarios!$B$8,Scenarios!$B$2,Scenarios!$C$2,Scenarios!$D$2) -> 15000 | L10: =15000*CHOOSE(Scenarios!$B$8,Scenarios!$B$2,Scenarios!$C$2,Scenarios!$D$2) -> 15000 | M10: =16250*CHOOSE(Scenarios!$B$8,Scenarios!$B$2,Scenarios!$C$2,Scenarios!$D$2) -> 16250 | N10: =16250*CHOOSE(Scenarios!$B$8,Scenarios!$B$2,Scenarios!$C$2,Scenarios!$D$2) -> 16250 | O10: =16250*CHOOSE(Scenarios!$B$8,Scenarios!$B$2,Scenarios!$C$2,Scenarios!$D$2) -> 16250 | P10: =17500*CHOOSE(Scenarios!$B$8,Scenarios!$B$2,Scenarios!$C$2,Scenarios!$D$2) -> 17500 | Q10: =17500*CHOOSE(Scenarios!$B$8,Scenarios!$B$2,Scenarios!$C$2,Scenarios!$D$2) -> 17500 | R10: =SUM(F10:Q10) -> 162500 | U10: 2028 | V10: =SUM(R35:R37) -> 915500 | W10: =SUM(R38:R40) -> 246228.12 | X10: =R53 -> 52495.254 | Y10: =X10/W10 -> 0.21319763 | Z10: =SUM(R48:R50) -> 135532.96 | AC10: =$R$20/(Assumptions!$M$20-'Стоимость производства'!$H$34) -> 459.78903
E11: Oral-B Pro-Clinic Caries Defense | F11: =3000*CHOOSE(Scenarios!$B$8,Scenarios!$B$2,Scenarios!$C$2,Scenarios!$D$2) -> 3000 | G11: =4500*CHOOSE(Scenarios!$B$8,Scenarios!$B$2,Scenarios!$C$2,Scenarios!$D$2) -> 4500 | H11: =6000*CHOOSE(Scenarios!$B$8,Scenarios!$B$2,Scenarios!$C$2,Scenarios!$D$2) -> 6000 | I11: =7500*CHOOSE(Scenarios!$B$8,Scenarios!$B$2,Scenarios!$C$2,Scenarios!$D$2) -> 7500 | J11: =8250*CHOOSE(Scenarios!$B$8,Scenarios!$B$2,Scenarios!$C$2,Scenarios!$D$2) -> 8250 | K11: =9000*CHOOSE(Scenarios!$B$8,Scenarios!$B$2,Scenarios!$C$2,Scenarios!$D$2) -> 9000 | L11: =9000*CHOOSE(Scenarios!$B$8,Scenarios!$B$2,Scenarios!$C$2,Scenarios!$D$2) -> 9000 | M11: =9750*CHOOSE(Scenarios!$B$8,Scenarios!$B$2,Scenarios!$C$2,Scenarios!$D$2) -> 9750 | N11: =9750*CHOOSE(Scenarios!$B$8,Scenarios!$B$2,Scenarios!$C$2,Scenarios!$D$2) -> 9750 | O11: =9750*CHOOSE(Scenarios!$B$8,Scenarios!$B$2,Scenarios!$C$2,Scenarios!$D$2) -> 9750 | P11: =10500*CHOOSE(Scenarios!$B$8,Scenarios!$B$2,Scenarios!$C$2,Scenarios!$D$2) -> 10500 | Q11: =10500*CHOOSE(Scenarios!$B$8,Scenarios!$B$2,Scenarios!$C$2,Scenarios!$D$2) -> 10500 | R11: =SUM(F11:Q11) -> 97500 | U11: 2029 | V11: =SUM(R61:R63) -> 996000 | W11: =SUM(R64:R66) -> 268108.75 | X11: =R79 -> 53452.127 | Y11: =X11/W11 -> 0.19936734 | Z11: =SUM(R74:R76) -> 140342.41 | AC11: =$R$20/(Assumptions!$M$21-'Стоимость производства'!$H$61) -> 397.85246
D12: Выручка ( без НДС, тыс. руб ) | E12: Oral-B Pro-Clinic Total Restore | F12: =F9/1000*Assumptions!$M$19 -> 3185 | G12: =G9/1000*Assumptions!$M$19 -> 4777.5 | H12: =H9/1000*Assumptions!$M$19 -> 6370 | I12: =I9/1000*Assumptions!$M$19 -> 7962.5 | J12: =J9/1000*Assumptions!$M$19 -> 8758.75 | K12: =K9/1000*Assumptions!$M$19 -> 9555 | L12: =L9/1000*Assumptions!$M$19 -> 9555 | M12: =M9/1000*Assumptions!$M$19 -> 10351.25 | ... Q12: =Q9/1000*Assumptions!$M$19 -> 11147.5 | R12: =SUM(F12:Q12) -> 103512.5 | U12: 2030 | V12: =SUM(R87:R89) -> 999000 | W12: =SUM(R90:R92) -> 301161.25 | X12: =R105 -> 69370.138 | Y12: =X12/W12 -> 0.23034218 | Z12: =SUM(R100:R102) -> 165312.06
E13: Oral-B Pro-Clinic Sensitive Shield | F13: =F10/1000*Assumptions!$M$20 -> 1191.6667 | G13: =G10/1000*Assumptions!$M$20 -> 1787.5 | H13: =H10/1000*Assumptions!$M$20 -> 2383.3333 | I13: =I10/1000*Assumptions!$M$20 -> 2979.1667 | J13: =J10/1000*Assumptions!$M$20 -> 3277.0833 | K13: =K10/1000*Assumptions!$M$20 -> 3575 | L13: =L10/1000*Assumptions!$M$20 -> 3575 | M13: =M10/1000*Assumptions!$M$20 -> 3872.9167 | ... Q13: =Q10/1000*Assumptions!$M$20 -> 4170.8333 | R13: =SUM(F13:Q13) -> 38729.167 | U13: 2031 | V13: =SUM(R113:R115) -> 999000 | W13: =SUM(R116:R118) -> 301161.25 | X13: =R131 -> 65733.047 | Y13: =X13/W13 -> 0.21826529 | Z13: =SUM(R126:R128) -> 157161.11
E14: Oral-B Pro-Clinic Caries Defense | F14: =F11/1000*Assumptions!$M$21 -> 715 | G14: =G11/1000*Assumptions!$M$21 -> 1072.5 | H14: =H11/1000*Assumptions!$M$21 -> 1430 | I14: =I11/1000*Assumptions!$M$21 -> 1787.5 | J14: =J11/1000*Assumptions!$M$21 -> 1966.25 | K14: =K11/1000*Assumptions!$M$21 -> 2145 | L14: =L11/1000*Assumptions!$M$21 -> 2145 | M14: =M11/1000*Assumptions!$M$21 -> 2323.75 | ... Q14: =Q11/1000*Assumptions!$M$21 -> 2502.5 | R14: =SUM(F14:Q14) -> 23237.5
D15: Прямые расходы (COGS) | E15: Oral-B Pro-Clinic Total Restore | F15: =(F9/1000) * 'Стоимость производства'!$H$12 -> 1400.0547 | G15: =(G9/1000) * 'Стоимость производства'!$H$12 -> 2100.0821 | H15: =(H9/1000) * 'Стоимость производства'!$H$12 -> 2800.1094 | I15: =(I9/1000) * 'Стоимость производства'!$H$12 -> 3500.1368 | J15: =(J9/1000) * 'Стоимость производства'!$H$12 -> 3850.1504 | K15: =(K9/1000) * 'Стоимость производства'!$H$12 -> 4200.1641 | L15: =(L9/1000) * 'Стоимость производства'!$H$12 -> 4200.1641 | M15: =(M9/1000) * 'Стоимость производства'!$H$12 -> 4550.1778 | ... Q15: =(Q9/1000) * 'Стоимость производства'!$H$12 -> 4900.1915 | R15: =SUM(F15:Q15) -> 45501.778
E16: Oral-B Pro-Clinic Sensitive Shield | F16: =F10/1000 * 'Стоимость производства'!$H$34 -> 587.47652 | G16: =G10/1000 * 'Стоимость производства'!$H$34 -> 881.21478 | H16: =H10/1000 * 'Стоимость производства'!$H$34 -> 1174.953 | I16: =I10/1000 * 'Стоимость производства'!$H$34 -> 1468.6913 | J16: =J10/1000 * 'Стоимость производства'!$H$34 -> 1615.5604 | K16: =K10/1000 * 'Стоимость производства'!$H$34 -> 1762.4296 | L16: =L10/1000 * 'Стоимость производства'!$H$34 -> 1762.4296 | M16: =M10/1000 * 'Стоимость производства'!$H$34 -> 1909.2987 | ... Q16: =Q10/1000 * 'Стоимость производства'!$H$34 -> 2056.1678 | R16: =SUM(F16:Q16) -> 19092.987
E17: Oral-B Pro-Clinic Caries Defense | F17: =('Стоимость производства'!$H$61)*'P&L'!F11/1000 -> 296.05072 | G17: =('Стоимость производства'!$H$61)*'P&L'!G11/1000 -> 444.07609 | H17: =('Стоимость производства'!$H$61)*'P&L'!H11/1000 -> 592.10145 | I17: =('Стоимость производства'!$H$61)*'P&L'!I11/1000 -> 740.12681 | J17: =('Стоимость производства'!$H$61)*'P&L'!J11/1000 -> 814.13949 | K17: =('Стоимость производства'!$H$61)*'P&L'!K11/1000 -> 888.15217 | L17: =('Стоимость производства'!$H$61)*'P&L'!L11/1000 -> 888.15217 | M17: =('Стоимость производства'!$H$61)*'P&L'!M11/1000 -> 962.16485 | ... Q17: =('Стоимость производства'!$H$61)*'P&L'!Q11/1000 -> 1036.1775 | R17: =SUM(F17:Q17) -> 9621.6485
D18: Расходы на продвижение (Маркетинг) | F18: =Assumptions!$F$32 -> 1830 | G18: =Assumptions!$F$32 -> 1830 | H18: =Assumptions!$F$32 -> 1830 | I18: =Assumptions!$F$32 -> 1830 | J18: =Assumptions!$F$32 -> 1830 | K18: =Assumptions!$F$32 -> 1830 | L18: =Assumptions!$F$32 -> 1830 | M18: =Assumptions!$F$32 -> 1830 | ... Q18: =Assumptions!$F$32 -> 1830 | R18: =SUM(F18:Q18) -> 21960
D19: Амортизация | F19: =Assumptions!$B$43 -> 553.80754 | G19: =Assumptions!$B$43 -> 553.80754 | H19: =Assumptions!$B$43 -> 553.80754 | I19: =Assumptions!$B$43 -> 553.80754 | J19: =Assumptions!$B$43 -> 553.80754 | K19: =Assumptions!$B$43 -> 553.80754 | L19: =Assumptions!$B$43 -> 553.80754 | M19: =Assumptions!$B$43 -> 553.80754 | ... Q19: =Assumptions!$B$43 -> 553.80754 | R19: =Q19*12 -> 6645.6905
D20: OPEX | F20: =Assumptions!$F$39 -> 4630 | G20: =Assumptions!$F$39 -> 4630 | H20: =Assumptions!$F$39 -> 4630 | I20: =Assumptions!$F$39 -> 4630 | J20: =Assumptions!$F$39 -> 4630 | K20: =Assumptions!$F$39 -> 4630 | L20: =Assumptions!$F$39 -> 4630 | M20: =Assumptions!$F$39 -> 4630 | ... Q20: =Assumptions!$F$39 -> 4630 | R20: =SUM(F20:Q20) -> 55560
D21: EBIT | F21: =SUM(F22:F24) - F20 - F19 -> -2375.7228 | G21: =SUM(G22:G24) - G20 - G19 -> -971.68046 | H21: =SUM(H22:H24) - H20 - H19 -> 432.3619 | I21: =SUM(I22:I24) - I20 - I19 -> 1836.4043 | J21: =SUM(J22:J24) - J20 - J19 -> 2538.4254 | K21: =SUM(K22:K24) - K20 - K19 -> 3240.4466 | L21: =SUM(L22:L24) - L20 - L19 -> 3240.4466 | M21: =SUM(M22:M24) - M20 - M19 -> 3942.4678 | ... R21: =SUM(R22:R24) - R20 - R19 -> 29057.063
D22: Маржинальная прибыль | E22: Oral-B Pro-Clinic Total Restore | F22: =F12-F15 -> 1784.9453 | G22: =G12-G15 -> 2677.4179 | H22: =H12-H15 -> 3569.8906 | I22: =I12-I15 -> 4462.3632 | J22: =J12-J15 -> 4908.5996 | K22: =K12-K15 -> 5354.8359 | L22: =L12-L15 -> 5354.8359 | M22: =M12-M15 -> 5801.0722 | ... Q22: =Q12-Q15 -> 6247.3085 | R22: =SUM(F22:Q22) -> 58010.722
E23: Oral-B Pro-Clinic Sensitive Shield | F23: =F13-F16 -> 604.19015 | G23: =G13-G16 -> 906.28522 | H23: =H13-H16 -> 1208.3803 | I23: =I13-I16 -> 1510.4754 | J23: =J13-J16 -> 1661.5229 | K23: =K13-K16 -> 1812.5704 | L23: =L13-L16 -> 1812.5704 | M23: =M13-M16 -> 1963.618 | ... Q23: =Q13-Q16 -> 2114.6655 | R23: =SUM(F23:Q23) -> 19636.18
E24: Oral-B Pro-Clinic Caries Defense | F24: =F14-F17 -> 418.94928 | G24: =G14-G17 -> 628.42391 | H24: =H14-H17 -> 837.89855 | I24: =I14-I17 -> 1047.3732 | J24: =J14-J17 -> 1152.1105 | K24: =K14-K17 -> 1256.8478 | L24: =L14-L17 -> 1256.8478 | M24: =M14-M17 -> 1361.5851 | ... Q24: =Q14-Q17 -> 1466.3225 | R24: =SUM(F24:Q24) -> 13615.851
D25: EBITDA | F25: =F27+F19+F26 -> -1821.9153 | G25: =G27+G19+G26 -> -417.87292 | H25: =H27+H19+H26 -> 986.16944 | I25: =I27+I19+I26 -> 2390.2118 | J25: =J27+J19+J26 -> 3092.233 | K25: =K27+K19+K26 -> 3794.2542 | L25: =L27+L19+L26 -> 3794.2542 | M25: =M27+M19+M26 -> 4496.2753 | ... Q25: =Q27+Q19+Q26 -> 5198.2965 | R25: =SUM(F25:Q25) -> 35702.753
D26: Налог на прибыль | F26: =MAX(0,F21*Assumptions!$B$10) -> 0 | G26: =MAX(0,G21*Assumptions!$B$10) -> 0 | H26: =MAX(0,H21*Assumptions!$B$10) -> 108.09047 | I26: =MAX(0,I21*Assumptions!$B$10) -> 459.10106 | J26: =MAX(0,J21*Assumptions!$B$10) -> 634.60636 | K26: =MAX(0,K21*Assumptions!$B$10) -> 810.11165 | L26: =MAX(0,L21*Assumptions!$B$10) -> 810.11165 | M26: =MAX(0,M21*Assumptions!$B$10) -> 985.61695 | ... Q26: =MAX(0,Q21*Assumptions!$B$10) -> 1161.1222 | R26: =SUM(F26:Q26) -> 8101.1165
D27: Net Profit | F27: =F21-F26 -> -2375.7228 | G27: =G21-G26 -> -971.68046 | H27: =H21-H26 -> 324.27142 | I27: =I21-I26 -> 1377.3032 | J27: =J21-J26 -> 1903.8191 | K27: =K21-K26 -> 2430.335 | L27: =L21-L26 -> 2430.335 | M27: =M21-M26 -> 2956.8508 | ... Q27: =Q21-Q26 -> 3483.3667 | R27: =SUM(F27:Q27) -> 20955.946
D33: Прогноз на 2028 год
F34: 46023 | G34: 46054 | H34: 46082 | I34: 46113 | J34: 46143 | K34: 46174 | L34: 46204 | M34: 46235 | N34: 46266 | O34: 46296 | P34: 46327 | Q34: 46357 | R34: Итог
D35: Объем продаж | E35: Oral-B Pro-Clinic Total Restore | F35: =42500*CHOOSE(Scenarios!$B$8,Scenarios!$B$2,Scenarios!$C$2,Scenarios!$D$2) -> 42500 | G35: =43000*CHOOSE(Scenarios!$B$8,Scenarios!$B$2,Scenarios!$C$2,Scenarios!$D$2) -> 43000 | H35: =43500*CHOOSE(Scenarios!$B$8,Scenarios!$B$2,Scenarios!$C$2,Scenarios!$D$2) -> 43500 | I35: =44000*CHOOSE(Scenarios!$B$8,Scenarios!$B$2,Scenarios!$C$2,Scenarios!$D$2) -> 44000 | J35: =44500*CHOOSE(Scenarios!$B$8,Scenarios!$B$2,Scenarios!$C$2,Scenarios!$D$2) -> 44500 | K35: =45000*CHOOSE(Scenarios!$B$8,Scenarios!$B$2,Scenarios!$C$2,Scenarios!$D$2) -> 45000 | L35: =45500*CHOOSE(Scenarios!$B$8,Scenarios!$B$2,Scenarios!$C$2,Scenarios!$D$2) -> 45500 | M35: =46000*CHOOSE(Scenarios!$B$8,Scenarios!$B$2,Scenarios!$C$2,Scenarios!$D$2) -> 46000 | N35: =46500*CHOOSE(Scenarios!$B$8,Scenarios!$B$2,Scenarios!$C$2,Scenarios!$D$2) -> 46500 | O35: =47000*CHOOSE(Scenarios!$B$8,Scenarios!$B$2,Scenarios!$C$2,Scenarios!$D$2) -> 47000 | P35: =47500*CHOOSE(Scenarios!$B$8,Scenarios!$B$2,Scenarios!$C$2,Scenarios!$D$2) -> 47500 | Q35: =48000*CHOOSE(Scenarios!$B$8,Scenarios!$B$2,Scenarios!$C$2,Scenarios!$D$2) -> 48000 | R35: =SUM(F35:Q35) -> 543000
E36: Oral-B Pro-Clinic Sensitive Shield | F36: =17750*CHOOSE(Scenarios!$B$8,Scenarios!$B$2,Scenarios!$C$2,Scenarios!$D$2) -> 17750 | G36: =18000*CHOOSE(Scenarios!$B$8,Scenarios!$B$2,Scenarios!$C$2,Scenarios!$D$2) -> 18000 | H36: =18250*CHOOSE(Scenarios!$B$8,Scenarios!$B$2,Scenarios!$C$2,Scenarios!$D$2) -> 18250 | I36: =18500*CHOOSE(Scenarios!$B$8,Scenarios!$B$2,Scenarios!$C$2,Scenarios!$D$2) -> 18500 | J36: =18750*CHOOSE(Scenarios!$B$8,Scenarios!$B$2,Scenarios!$C$2,Scenarios!$D$2) -> 18750 | K36: =19000*CHOOSE(Scenarios!$B$8,Scenarios!$B$2,Scenarios!$C$2,Scenarios!$D$2) -> 19000 | L36: =19250*CHOOSE(Scenarios!$B$8,Scenarios!$B$2,Scenarios!$C$2,Scenarios!$D$2) -> 19250 | M36: =19500*CHOOSE(Scenarios!$B$8,Scenarios!$B$2,Scenarios!$C$2,Scenarios!$D$2) -> 19500 | N36: =19750*CHOOSE(Scenarios!$B$8,Scenarios!$B$2,Scenarios!$C$2,Scenarios!$D$2) -> 19750 | O36: =20000*CHOOSE(Scenarios!$B$8,Scenarios!$B$2,Scenarios!$C$2,Scenarios!$D$2) -> 20000 | P36: =20250*CHOOSE(Scenarios!$B$8,Scenarios!$B$2,Scenarios!$C$2,Scenarios!$D$2) -> 20250 | Q36: =20500*CHOOSE(Scenarios!$B$8,Scenarios!$B$2,Scenarios!$C$2,Scenarios!$D$2) -> 20500 | R36: =SUM(F36:Q36) -> 229500
E37: Oral-B Pro-Clinic Caries Defense | F37: =10750*CHOOSE(Scenarios!$B$8,Scenarios!$B$2,Scenarios!$C$2,Scenarios!$D$2) -> 10750 | G37: =11000*CHOOSE(Scenarios!$B$8,Scenarios!$B$2,Scenarios!$C$2,Scenarios!$D$2) -> 11000 | H37: =11250*CHOOSE(Scenarios!$B$8,Scenarios!$B$2,Scenarios!$C$2,Scenarios!$D$2) -> 11250 | I37: =11500*CHOOSE(Scenarios!$B$8,Scenarios!$B$2,Scenarios!$C$2,Scenarios!$D$2) -> 11500 | J37: =11750*CHOOSE(Scenarios!$B$8,Scenarios!$B$2,Scenarios!$C$2,Scenarios!$D$2) -> 11750 | K37: =12000*CHOOSE(Scenarios!$B$8,Scenarios!$B$2,Scenarios!$C$2,Scenarios!$D$2) -> 12000 | L37: =12250*CHOOSE(Scenarios!$B$8,Scenarios!$B$2,Scenarios!$C$2,Scenarios!$D$2) -> 12250 | M37: =12500*CHOOSE(Scenarios!$B$8,Scenarios!$B$2,Scenarios!$C$2,Scenarios!$D$2) -> 12500 | N37: =12500*CHOOSE(Scenarios!$B$8,Scenarios!$B$2,Scenarios!$C$2,Scenarios!$D$2) -> 12500 | O37: =12500*CHOOSE(Scenarios!$B$8,Scenarios!$B$2,Scenarios!$C$2,Scenarios!$D$2) -> 12500 | P37: =12500*CHOOSE(Scenarios!$B$8,Scenarios!$B$2,Scenarios!$C$2,Scenarios!$D$2) -> 12500 | Q37: =12500*CHOOSE(Scenarios!$B$8,Scenarios!$B$2,Scenarios!$C$2,Scenarios!$D$2) -> 12500 | R37: =SUM(F37:Q37) -> 143000
D38: Выручка ( без НДС, тыс. руб ) | E38: Oral-B Pro-Clinic Total Restore | F38: =F35/1000*Assumptions!$O$19 -> 11970.833 | G38: =G35/1000*Assumptions!$O$19 -> 12111.667 | H38: =H35/1000*Assumptions!$O$19 -> 12252.5 | I38: =I35/1000*Assumptions!$O$19 -> 12393.333 | J38: =J35/1000*Assumptions!$O$19 -> 12534.167 | K38: =K35/1000*Assumptions!$O$19 -> 12675 | L38: =L35/1000*Assumptions!$O$19 -> 12815.833 | M38: =M35/1000*Assumptions!$O$19 -> 12956.667 | ... Q38: =Q35/1000*Assumptions!$O$19 -> 13520 | R38: =SUM(F38:Q38) -> 152945
E39: Oral-B Pro-Clinic Sensitive Shield | F39: =F36/1000*Assumptions!$O$20 -> 4518.8542 | G39: =G36/1000*Assumptions!$O$20 -> 4582.5 | H39: =H36/1000*Assumptions!$O$20 -> 4646.1458 | I39: =I36/1000*Assumptions!$O$20 -> 4709.7917 | J39: =J36/1000*Assumptions!$O$20 -> 4773.4375 | K39: =K36/1000*Assumptions!$O$20 -> 4837.0833 | L39: =L36/1000*Assumptions!$O$20 -> 4900.7292 | M39: =M36/1000*Assumptions!$O$20 -> 4964.375 | ... Q39: =Q36/1000*Assumptions!$O$20 -> 5218.9583 | R39: =SUM(F39:Q39) -> 58426.875
E40: Oral-B Pro-Clinic Caries Defense | F40: =F37/1000*Assumptions!$O$21 -> 2620.3125 | G40: =G37/1000*Assumptions!$O$21 -> 2681.25 | H40: =H37/1000*Assumptions!$O$21 -> 2742.1875 | I40: =I37/1000*Assumptions!$O$21 -> 2803.125 | J40: =J37/1000*Assumptions!$O$21 -> 2864.0625 | K40: =K37/1000*Assumptions!$O$21 -> 2925 | L40: =L37/1000*Assumptions!$O$21 -> 2985.9375 | M40: =M37/1000*Assumptions!$O$21 -> 3046.875 | ... Q40: =Q37/1000*Assumptions!$O$21 -> 3046.875 | R40: =SUM(F40:Q40) -> 34856.25
D41: Прямые расходы (COGS) | E41: Oral-B Pro-Clinic Total Restore | F41: =(F35/1000) * 'Стоимость производства'!$H$12 * 1.06 -> 5256.0387 | G41: =(G35/1000) * 'Стоимость производства'!$H$12 * 1.06 -> 5317.8745 | H41: =(H35/1000) * 'Стоимость производства'!$H$12 * 1.06 -> 5379.7102 | I41: =(I35/1000) * 'Стоимость производства'!$H$12 * 1.06 -> 5441.546 | J41: =(J35/1000) * 'Стоимость производства'!$H$12 * 1.06 -> 5503.3817 | K41: =(K35/1000) * 'Стоимость производства'!$H$12 * 1.06 -> 5565.2175 | L41: =(L35/1000) * 'Стоимость производства'!$H$12 * 1.06 -> 5627.0532 | M41: =(M35/1000) * 'Стоимость производства'!$H$12 * 1.06 -> 5688.889 | ... Q41: =(Q35/1000) * 'Стоимость производства'!$H$12 * 1.06 -> 5936.232 | R41: =SUM(F41:Q41) -> 67153.624
E42: Oral-B Pro-Clinic Sensitive Shield | F42: ='Стоимость производства'!$H$34*'P&L'!F36 /1000 * 1.06 -> 2210.6741 | G42: ='Стоимость производства'!$H$34*'P&L'!G36 /1000 * 1.06 -> 2241.8104 | H42: ='Стоимость производства'!$H$34*'P&L'!H36 /1000 * 1.06 -> 2272.9467 | I42: ='Стоимость производства'!$H$34*'P&L'!I36 /1000 * 1.06 -> 2304.0829 | J42: ='Стоимость производства'!$H$34*'P&L'!J36 /1000 * 1.06 -> 2335.2192 | K42: ='Стоимость производства'!$H$34*'P&L'!K36 /1000 * 1.06 -> 2366.3554 | L42: ='Стоимость производства'!$H$34*'P&L'!L36 /1000 * 1.06 -> 2397.4917 | M42: ='Стоимость производства'!$H$34*'P&L'!M36 /1000 * 1.06 -> 2428.6279 | ... Q42: ='Стоимость производства'!$H$34*'P&L'!Q36 /1000 * 1.06 -> 2553.173 | R42: =SUM(F42:Q42) -> 28583.083
E43: Oral-B Pro-Clinic Caries Defense | F43: =('Стоимость производства'!$H$61)*'P&L'!F37/1000 * 1.06 -> 1124.4993 | G43: =('Стоимость производства'!$H$61)*'P&L'!G37/1000 * 1.06 -> 1150.6505 | H43: =('Стоимость производства'!$H$61)*'P&L'!H37/1000 * 1.06 -> 1176.8016 | I43: =('Стоимость производства'!$H$61)*'P&L'!I37/1000 * 1.06 -> 1202.9528 | J43: =('Стоимость производства'!$H$61)*'P&L'!J37/1000 * 1.06 -> 1229.1039 | K43: =('Стоимость производства'!$H$61)*'P&L'!K37/1000 * 1.06 -> 1255.2551 | L43: =('Стоимость производства'!$H$61)*'P&L'!L37/1000 * 1.06 -> 1281.4062 | M43: =('Стоимость производства'!$H$61)*'P&L'!M37/1000 * 1.06 -> 1307.5574 | ... Q43: =('Стоимость производства'!$H$61)*'P&L'!Q37/1000 * 1.06 -> 1307.5574 | R43: =SUM(F43:Q43) -> 14958.456
D44: Расходы на продвижение (Маркетинг) | F44: =Assumptions!$F$32 -> 1830 | G44: =Assumptions!$F$32 -> 1830 | H44: =Assumptions!$F$32 -> 1830 | I44: =Assumptions!$F$32 -> 1830 | J44: =Assumptions!$F$32 -> 1830 | K44: =Assumptions!$F$32 -> 1830 | L44: =Assumptions!$F$32 -> 1830 | M44: =Assumptions!$F$32 -> 1830 | ... Q44: =Assumptions!$F$32 -> 1830 | R44: =SUM(F44:Q44) -> 21960
D45: Амортизация | F45: =Assumptions!$B$43 -> 553.80754 | G45: =Assumptions!$B$43 -> 553.80754 | H45: =Assumptions!$B$43 -> 553.80754 | I45: =Assumptions!$B$43 -> 553.80754 | J45: =Assumptions!$B$43 -> 553.80754 | K45: =Assumptions!$B$43 -> 553.80754 | L45: =Assumptions!$B$43 -> 553.80754 | M45: =Assumptions!$B$43 -> 553.80754 | ... Q45: =Assumptions!$B$43 -> 553.80754 | R45: =SUM(F45:Q45) -> 6645.6905
D46: OPEX | F46: =Assumptions!$F$39 * 1.06 -> 4907.8 | G46: =Assumptions!$F$39 * 1.06 -> 4907.8 | H46: =Assumptions!$F$39 * 1.06 -> 4907.8 | I46: =Assumptions!$F$39 * 1.06 -> 4907.8 | J46: =Assumptions!$F$39 * 1.06 -> 4907.8 | K46: =Assumptions!$F$39 * 1.06 -> 4907.8 | L46: =Assumptions!$F$39 * 1.06 -> 4907.8 | M46: =Assumptions!$F$39 * 1.06 -> 4907.8 | ... Q46: =Assumptions!$F$39 * 1.06 -> 4907.8 | R46: =SUM(F46:Q46) -> 58893.6
D47: EBIT | F47: =SUM(F48:F50) - F46 - F45 -> 5057.1803 | G47: =SUM(G48:G50) - G46 - G45 -> 5203.4738 | H47: =SUM(H48:H50) - H46 - H45 -> 5349.7673 | I47: =SUM(I48:I50) - I46 - I45 -> 5496.0608 | J47: =SUM(J48:J50) - J46 - J45 -> 5642.3543 | K47: =SUM(K48:K50) - K46 - K45 -> 5788.6478 | L47: =SUM(L48:L50) - L46 - L45 -> 5934.9414 | M47: =SUM(M48:M50) - M46 - M45 -> 6081.2349 | ... R47: =SUM(R48:R50) - R46 - R45 -> 69993.672
D48: Маржинальная прибыль | E48: Oral-B Pro-Clinic Total Restore | F48: =F38-F41 -> 6714.7946 | G48: =G38-G41 -> 6793.7922 | H48: =H38-H41 -> 6872.7898 | I48: =I38-I41 -> 6951.7874 | J48: =J38-J41 -> 7030.785 | K48: =K38-K41 -> 7109.7825 | L48: =L38-L41 -> 7188.7801 | M48: =M38-M41 -> 7267.7777 | ... Q48: =Q38-Q41 -> 7583.768 | R48: =SUM(F48:Q48) -> 85791.376
E49: Oral-B Pro-Clinic Sensitive Shield | F49: =F39-F42 -> 2308.18 | G49: =G39-G42 -> 2340.6896 | H49: =H39-H42 -> 2373.1992 | I49: =I39-I42 -> 2405.7088 | J49: =J39-J42 -> 2438.2183 | K49: =K39-K42 -> 2470.7279 | L49: =L39-L42 -> 2503.2375 | M49: =M39-M42 -> 2535.7471 | ... Q49: =Q39-Q42 -> 2665.7854 | R49: =SUM(F49:Q49) -> 29843.792
E50: Oral-B Pro-Clinic Caries Defense | F50: =F40-F43 -> 1495.8132 | G50: =G40-G43 -> 1530.5995 | H50: =H40-H43 -> 1565.3859 | I50: =I40-I43 -> 1600.1722 | J50: =J40-J43 -> 1634.9586 | K50: =K40-K43 -> 1669.7449 | L50: =L40-L43 -> 1704.5313 | M50: =M40-M43 -> 1739.3176 | ... Q50: =Q40-Q43 -> 1739.3176 | R50: =SUM(F50:Q50) -> 19897.794
D51: EBITDA | F51: =F53+F45+F52 -> 5610.9878 | G51: =G53+G45+G52 -> 5757.2813 | H51: =H53+H45+H52 -> 5903.5748 | I51: =I53+I45+I52 -> 6049.8684 | J51: =J53+J45+J52 -> 6196.1619 | K51: =K53+K45+K52 -> 6342.4554 | L51: =L53+L45+L52 -> 6488.7489 | M51: =M53+M45+M52 -> 6635.0424 | ... Q51: =Q53+Q45+Q52 -> 7081.0711
D52: Налог на прибыль | F52: =MAX(0,F47*Assumptions!$B$10) -> 1264.2951 | G52: =MAX(0,G47*Assumptions!$B$10) -> 1300.8684 | H52: =MAX(0,H47*Assumptions!$B$10) -> 1337.4418 | I52: =MAX(0,I47*Assumptions!$B$10) -> 1374.0152 | J52: =MAX(0,J47*Assumptions!$B$10) -> 1410.5886 | K52: =MAX(0,K47*Assumptions!$B$10) -> 1447.162 | L52: =MAX(0,L47*Assumptions!$B$10) -> 1483.7353 | M52: =MAX(0,M47*Assumptions!$B$10) -> 1520.3087 | ... Q52: =MAX(0,Q47*Assumptions!$B$10) -> 1631.8159 | R52: =SUM(F52:Q52) -> 17498.418
D53: Net Profit | F53: =F47-F52 -> 3792.8852 | G53: =G47-G52 -> 3902.6053 | H53: =H47-H52 -> 4012.3255 | I53: =I47-I52 -> 4122.0456 | J53: =J47-J52 -> 4231.7658 | K53: =K47-K52 -> 4341.4859 | L53: =L47-L52 -> 4451.206 | M53: =M47-M52 -> 4560.9262 | ... Q53: =Q47-Q52 -> 4895.4476 | R53: =SUM(F53:Q53) -> 52495.254
D59: Прогноз на 2029 год
F60: 46023 | G60: 46054 | H60: 46082 | I60: 46113 | J60: 46143 | K60: 46174 | L60: 46204 | M60: 46235 | N60: 46266 | O60: 46296 | P60: 46327 | Q60: 46357 | R60: Итог (тыс. руб)
D61: Объем продаж | E61: Oral-B Pro-Clinic Total Restore | F61: =48500*CHOOSE(Scenarios!$B$8,Scenarios!$B$3,Scenarios!$C$3,Scenarios!$D$3) -> 48500 | G61: =49000*CHOOSE(Scenarios!$B$8,Scenarios!$B$3,Scenarios!$C$3,Scenarios!$D$3) -> 49000 | H61: =49500*CHOOSE(Scenarios!$B$8,Scenarios!$B$3,Scenarios!$C$3,Scenarios!$D$3) -> 49500 | I61: =50000*CHOOSE(Scenarios!$B$8,Scenarios!$B$3,Scenarios!$C$3,Scenarios!$D$3) -> 50000 | J61: =50000*CHOOSE(Scenarios!$B$8,Scenarios!$B$3,Scenarios!$C$3,Scenarios!$D$3) -> 50000 | K61: =50000*CHOOSE(Scenarios!$B$8,Scenarios!$B$3,Scenarios!$C$3,Scenarios!$D$3) -> 50000 | L61: =50000*CHOOSE(Scenarios!$B$8,Scenarios!$B$3,Scenarios!$C$3,Scenarios!$D$3) -> 50000 | M61: =50000*CHOOSE(Scenarios!$B$8,Scenarios!$B$3,Scenarios!$C$3,Scenarios!$D$3) -> 50000 | N61: =50000*CHOOSE(Scenarios!$B$8,Scenarios!$B$3,Scenarios!$C$3,Scenarios!$D$3) -> 50000 | O61: =50000*CHOOSE(Scenarios!$B$8,Scenarios!$B$3,Scenarios!$C$3,Scenarios!$D$3) -> 50000 | P61: =50000*CHOOSE(Scenarios!$B$8,Scenarios!$B$3,Scenarios!$C$3,Scenarios!$D$3) -> 50000 | Q61: =50000*CHOOSE(Scenarios!$B$8,Scenarios!$B$3,Scenarios!$C$3,Scenarios!$D$3) -> 50000 | R61: =SUM(F61:Q61) -> 597000
E62: Oral-B Pro-Clinic Sensitive Shield | F62: =20750*CHOOSE(Scenarios!$B$8,Scenarios!$B$3,Scenarios!$C$3,Scenarios!$D$3) -> 20750 | G62: =20750*CHOOSE(Scenarios!$B$8,Scenarios!$B$3,Scenarios!$C$3,Scenarios!$D$3) -> 20750 | H62: =20750*CHOOSE(Scenarios!$B$8,Scenarios!$B$3,Scenarios!$C$3,Scenarios!$D$3) -> 20750 | I62: =20750*CHOOSE(Scenarios!$B$8,Scenarios!$B$3,Scenarios!$C$3,Scenarios!$D$3) -> 20750 | J62: =20750*CHOOSE(Scenarios!$B$8,Scenarios!$B$3,Scenarios!$C$3,Scenarios!$D$3) -> 20750 | K62: =20750*CHOOSE(Scenarios!$B$8,Scenarios!$B$3,Scenarios!$C$3,Scenarios!$D$3) -> 20750 | L62: =20750*CHOOSE(Scenarios!$B$8,Scenarios!$B$3,Scenarios!$C$3,Scenarios!$D$3) -> 20750 | M62: =20750*CHOOSE(Scenarios!$B$8,Scenarios!$B$3,Scenarios!$C$3,Scenarios!$D$3) -> 20750 | ... Q62: =20750*CHOOSE(Scenarios!$B$8,Scenarios!$B$3,Scenarios!$C$3,Scenarios!$D$3) -> 20750 | R62: =SUM(F62:Q62) -> 249000
E63: Oral-B Pro-Clinic Caries Defense | F63: =12500*CHOOSE(Scenarios!$B$8,Scenarios!$B$3,Scenarios!$C$3,Scenarios!$D$3) -> 12500 | G63: =12500*CHOOSE(Scenarios!$B$8,Scenarios!$B$3,Scenarios!$C$3,Scenarios!$D$3) -> 12500 | H63: =12500*CHOOSE(Scenarios!$B$8,Scenarios!$B$3,Scenarios!$C$3,Scenarios!$D$3) -> 12500 | I63: =12500*CHOOSE(Scenarios!$B$8,Scenarios!$B$3,Scenarios!$C$3,Scenarios!$D$3) -> 12500 | J63: =12500*CHOOSE(Scenarios!$B$8,Scenarios!$B$3,Scenarios!$C$3,Scenarios!$D$3) -> 12500 | K63: =12500*CHOOSE(Scenarios!$B$8,Scenarios!$B$3,Scenarios!$C$3,Scenarios!$D$3) -> 12500 | L63: =12500*CHOOSE(Scenarios!$B$8,Scenarios!$B$3,Scenarios!$C$3,Scenarios!$D$3) -> 12500 | M63: =12500*CHOOSE(Scenarios!$B$8,Scenarios!$B$3,Scenarios!$C$3,Scenarios!$D$3) -> 12500 | ... Q63: =12500*CHOOSE(Scenarios!$B$8,Scenarios!$B$3,Scenarios!$C$3,Scenarios!$D$3) -> 12500 | R63: =SUM(F63:Q63) -> 150000
D64: Выручка ( без НДС, тыс. руб ) | E64: Oral-B Pro-Clinic Total Restore | F64: =F61/1000*Assumptions!$O$19 -> 13660.833 | G64: =G61/1000*Assumptions!$O$19 -> 13801.667 | H64: =H61/1000*Assumptions!$O$19 -> 13942.5 | I64: =I61/1000*Assumptions!$O$19 -> 14083.333 | J64: =J61/1000*Assumptions!$O$19 -> 14083.333 | K64: =K61/1000*Assumptions!$O$19 -> 14083.333 | L64: =L61/1000*Assumptions!$O$19 -> 14083.333 | M64: =M61/1000*Assumptions!$O$19 -> 14083.333 | ... Q64: =Q61/1000*Assumptions!$O$19 -> 14083.333 | R64: =SUM(F64:Q64) -> 168155
E65: Oral-B Pro-Clinic Sensitive Shield | F65: =F62/1000*Assumptions!$O$20 -> 5282.6042 | G65: =G62/1000*Assumptions!$O$20 -> 5282.6042 | H65: =H62/1000*Assumptions!$O$20 -> 5282.6042 | I65: =I62/1000*Assumptions!$O$20 -> 5282.6042 | J65: =J62/1000*Assumptions!$O$20 -> 5282.6042 | K65: =K62/1000*Assumptions!$O$20 -> 5282.6042 | L65: =L62/1000*Assumptions!$O$20 -> 5282.6042 | M65: =M62/1000*Assumptions!$O$20 -> 5282.6042 | ... Q65: =Q62/1000*Assumptions!$O$20 -> 5282.6042 | R65: =SUM(F65:Q65) -> 63391.25
E66: Oral-B Pro-Clinic Caries Defense | F66: =F63/1000*Assumptions!$O$21 -> 3046.875 | G66: =G63/1000*Assumptions!$O$21 -> 3046.875 | H66: =H63/1000*Assumptions!$O$21 -> 3046.875 | I66: =I63/1000*Assumptions!$O$21 -> 3046.875 | J66: =J63/1000*Assumptions!$O$21 -> 3046.875 | K66: =K63/1000*Assumptions!$O$21 -> 3046.875 | L66: =L63/1000*Assumptions!$O$21 -> 3046.875 | M66: =M63/1000*Assumptions!$O$21 -> 3046.875 | ... Q66: =Q63/1000*Assumptions!$O$21 -> 3046.875 | R66: =SUM(F66:Q66) -> 36562.5
D67: Прямые расходы (COGS) | E67: Oral-B Pro-Clinic Total Restore | F67: =(F61/1000) * 'Стоимость производства'!$H$12 * 1.06*1.06 -> 6357.9518 | G67: =(G61/1000) * 'Стоимость производства'!$H$12 * 1.06*1.06 -> 6423.4977 | H67: =(H61/1000) * 'Стоимость производства'!$H$12 * 1.06*1.06 -> 6489.0436 | I67: =(I61/1000) * 'Стоимость производства'!$H$12 * 1.06*1.06 -> 6554.5894 | J67: =(J61/1000) * 'Стоимость производства'!$H$12 * 1.06*1.06 -> 6554.5894 | K67: =(K61/1000) * 'Стоимость производства'!$H$12 * 1.06*1.06 -> 6554.5894 | L67: =(L61/1000) * 'Стоимость производства'!$H$12 * 1.06*1.06 -> 6554.5894 | M67: =(M61/1000) * 'Стоимость производства'!$H$12 * 1.06*1.06 -> 6554.5894 | ... Q67: =(Q61/1000) * 'Стоимость производства'!$H$12 * 1.06*1.06 -> 6554.5894 | R67: =SUM(F67:Q67) -> 78261.798
E68: Oral-B Pro-Clinic Sensitive Shield | F68: ='Стоимость производства'!$H$34*'P&L'!F62 /1000* 1.06*1.06 -> 2739.3678 | G68: ='Стоимость производства'!$H$34*'P&L'!G62 /1000* 1.06*1.06 -> 2739.3678 | H68: ='Стоимость производства'!$H$34*'P&L'!H62 /1000* 1.06*1.06 -> 2739.3678 | I68: ='Стоимость производства'!$H$34*'P&L'!I62 /1000* 1.06*1.06 -> 2739.3678 | J68: ='Стоимость производства'!$H$34*'P&L'!J62 /1000* 1.06*1.06 -> 2739.3678 | K68: ='Стоимость производства'!$H$34*'P&L'!K62 /1000* 1.06*1.06 -> 2739.3678 | L68: ='Стоимость производства'!$H$34*'P&L'!L62 /1000* 1.06*1.06 -> 2739.3678 | M68: ='Стоимость производства'!$H$34*'P&L'!M62 /1000* 1.06*1.06 -> 2739.3678 | ... Q68: ='Стоимость производства'!$H$34*'P&L'!Q62 /1000* 1.06*1.06 -> 2739.3678 | R68: =SUM(F68:Q68) -> 32872.413
E69: Oral-B Pro-Clinic Caries Defense | F69: =('Стоимость производства'!$H$61)*'P&L'!F63/1000* 1.06*1.06 -> 1386.0108 | G69: =('Стоимость производства'!$H$61)*'P&L'!G63/1000* 1.06*1.06 -> 1386.0108 | H69: =('Стоимость производства'!$H$61)*'P&L'!H63/1000* 1.06*1.06 -> 1386.0108 | I69: =('Стоимость производства'!$H$61)*'P&L'!I63/1000* 1.06*1.06 -> 1386.0108 | J69: =('Стоимость производства'!$H$61)*'P&L'!J63/1000* 1.06*1.06 -> 1386.0108 | K69: =('Стоимость производства'!$H$61)*'P&L'!K63/1000* 1.06*1.06 -> 1386.0108 | L69: =('Стоимость производства'!$H$61)*'P&L'!L63/1000* 1.06*1.06 -> 1386.0108 | M69: =('Стоимость производства'!$H$61)*'P&L'!M63/1000* 1.06*1.06 -> 1386.0108 | ... Q69: =('Стоимость производства'!$H$61)*'P&L'!Q63/1000* 1.06*1.06 -> 1386.0108 | R69: =SUM(F69:Q69) -> 16632.13
D70: Расходы на продвижение | F70: =Assumptions!$F$32 -> 1830 | G70: =Assumptions!$F$32 -> 1830 | H70: =Assumptions!$F$32 -> 1830 | I70: =Assumptions!$F$32 -> 1830 | J70: =Assumptions!$F$32 -> 1830 | K70: =Assumptions!$F$32 -> 1830 | L70: =Assumptions!$F$32 -> 1830 | M70: =Assumptions!$F$32 -> 1830 | ... Q70: =Assumptions!$F$32 -> 1830 | R70: =SUM(F70:Q70) -> 21960
D71: Амортизация | F71: =Assumptions!$B$43 -> 553.80754 | G71: =Assumptions!$B$43 -> 553.80754 | H71: =Assumptions!$B$43 -> 553.80754 | I71: =Assumptions!$B$43 -> 553.80754 | J71: =Assumptions!$B$43 -> 553.80754 | K71: =Assumptions!$B$43 -> 553.80754 | L71: =Assumptions!$B$43 -> 553.80754 | M71: =Assumptions!$B$43 -> 553.80754 | ... Q71: =Assumptions!$B$43 -> 553.80754 | R71: =Q71*12 -> 6645.6905
D72: OPEX | F72: =Assumptions!$F$39* 1.06*1.06 -> 5202.268 | G72: =Assumptions!$F$39* 1.06*1.06 -> 5202.268 | H72: =Assumptions!$F$39* 1.06*1.06 -> 5202.268 | I72: =Assumptions!$F$39* 1.06*1.06 -> 5202.268 | J72: =Assumptions!$F$39* 1.06*1.06 -> 5202.268 | K72: =Assumptions!$F$39* 1.06*1.06 -> 5202.268 | L72: =Assumptions!$F$39* 1.06*1.06 -> 5202.268 | M72: =Assumptions!$F$39* 1.06*1.06 -> 5202.268 | ... Q72: =Assumptions!$F$39* 1.06*1.06 -> 5202.268 | R72: =SUM(F72:Q72) -> 62427.216
D73: EBIT | F73: =SUM(F74:F76) - F72 - F71 -> 5750.9066 | G73: =SUM(G74:G76) - G72 - G71 -> 5826.1941 | H73: =SUM(H74:H76) - H72 - H71 -> 5901.4815 | I73: =SUM(I74:I76) - I72 - I71 -> 5976.7689 | J73: =SUM(J74:J76) - J72 - J71 -> 5976.7689 | K73: =SUM(K74:K76) - K72 - K71 -> 5976.7689 | L73: =SUM(L74:L76) - L72 - L71 -> 5976.7689 | M73: =SUM(M74:M76) - M72 - M71 -> 5976.7689 | ... R73: =SUM(R74:R76) - R72 - R71 -> 71269.503
D74: Маржинальная прибыль | E74: Oral-B Pro-Clinic Total Restore | F74: =F64-F67 -> 7302.8816 | G74: =G64-G67 -> 7378.169 | H74: =H64-H67 -> 7453.4564 | I74: =I64-I67 -> 7528.7439 | J74: =J64-J67 -> 7528.7439 | K74: =K64-K67 -> 7528.7439 | L74: =L64-L67 -> 7528.7439 | M74: =M64-M67 -> 7528.7439 | ... Q74: =Q64-Q67 -> 7528.7439 | R74: =SUM(F74:Q74) -> 89893.202
E75: Oral-B Pro-Clinic Sensitive Shield | F75: =F65-F68 -> 2543.2364 | G75: =G65-G68 -> 2543.2364 | H75: =H65-H68 -> 2543.2364 | I75: =I65-I68 -> 2543.2364 | J75: =J65-J68 -> 2543.2364 | K75: =K65-K68 -> 2543.2364 | L75: =L65-L68 -> 2543.2364 | M75: =M65-M68 -> 2543.2364 | ... Q75: =Q65-Q68 -> 2543.2364 | R75: =SUM(F75:Q75) -> 30518.837
E76: Oral-B Pro-Clinic Caries Defense | F76: =F66-F69 -> 1660.8642 | G76: =G66-G69 -> 1660.8642 | H76: =H66-H69 -> 1660.8642 | I76: =I66-I69 -> 1660.8642 | J76: =J66-J69 -> 1660.8642 | K76: =K66-K69 -> 1660.8642 | L76: =L66-L69 -> 1660.8642 | M76: =M66-M69 -> 1660.8642 | ... Q76: =Q66-Q69 -> 1660.8642 | R76: =SUM(F76:Q76) -> 19930.37
D77: EBITDA | F77: =F79+F78+F71 -> 6304.7142 | G77: =G79+G78+G71 -> 6380.0016 | H77: =H79+H78+H71 -> 6455.289 | I77: =I79+I78+I71 -> 6530.5765 | J77: =J79+J78+J71 -> 6530.5765 | K77: =K79+K78+K71 -> 6530.5765 | L77: =L79+L78+L71 -> 6530.5765 | M77: =M79+M78+M71 -> 6530.5765 | ... Q77: =Q79+Q78+Q71 -> 6530.5765 | R77: =SUM(F77:Q77) -> 77915.193
D78: Налог на прибыль | F78: =MAX(0,F73*Assumptions!$B$10) -> 1437.7267 | G78: =MAX(0,G73*Assumptions!$B$10) -> 1456.5485 | H78: =MAX(0,H73*Assumptions!$B$10) -> 1475.3704 | I78: =MAX(0,I73*Assumptions!$B$10) -> 1494.1922 | J78: =MAX(0,J73*Assumptions!$B$10) -> 1494.1922 | K78: =MAX(0,K73*Assumptions!$B$10) -> 1494.1922 | L78: =MAX(0,L73*Assumptions!$B$10) -> 1494.1922 | M78: =MAX(0,M73*Assumptions!$B$10) -> 1494.1922 | ... Q78: =MAX(0,Q73*Assumptions!$B$10) -> 1494.1922 | R78: =SUM(F78:Q78) -> 17817.376
D79: Net Profit | F79: =F73-F78 -> 4313.18 | G79: =G73-G78 -> 4369.6456 | H79: =H73-H78 -> 4426.1111 | I79: =I73-I78 -> 4482.5767 | J79: =J73-J78 -> 4482.5767 | K79: =K73-K78 -> 4482.5767 | L79: =L73-L78 -> 4482.5767 | M79: =M73-M78 -> 4482.5767 | ... Q79: =Q73-Q78 -> 4482.5767 | R79: =SUM(F79:Q79) -> 53452.127
D85: Прогноз на 2030 год
F86: 46023 | G86: 46054 | H86: 46082 | I86: 46113 | J86: 46143 | K86: 46174 | L86: 46204 | M86: 46235 | N86: 46266 | O86: 46296 | P86: 46327 | Q86: 46357 | R86: Итог
D87: Объем продаж | E87: Oral-B Pro-Clinic Total Restore | F87: =50000*CHOOSE(Scenarios!$B$8,Scenarios!$B$3,Scenarios!$C$3,Scenarios!$D$3) -> 50000 | G87: =50000*CHOOSE(Scenarios!$B$8,Scenarios!$B$3,Scenarios!$C$3,Scenarios!$D$3) -> 50000 | H87: =50000*CHOOSE(Scenarios!$B$8,Scenarios!$B$3,Scenarios!$C$3,Scenarios!$D$3) -> 50000 | I87: =50000*CHOOSE(Scenarios!$B$8,Scenarios!$B$3,Scenarios!$C$3,Scenarios!$D$3) -> 50000 | J87: =50000*CHOOSE(Scenarios!$B$8,Scenarios!$B$3,Scenarios!$C$3,Scenarios!$D$3) -> 50000 | K87: =50000*CHOOSE(Scenarios!$B$8,Scenarios!$B$3,Scenarios!$C$3,Scenarios!$D$3) -> 50000 | L87: =50000*CHOOSE(Scenarios!$B$8,Scenarios!$B$3,Scenarios!$C$3,Scenarios!$D$3) -> 50000 | M87: =50000*CHOOSE(Scenarios!$B$8,Scenarios!$B$3,Scenarios!$C$3,Scenarios!$D$3) -> 50000 | ... Q87: =50000*CHOOSE(Scenarios!$B$8,Scenarios!$B$3,Scenarios!$C$3,Scenarios!$D$3) -> 50000 | R87: =SUM(F87:Q87) -> 600000
E88: Oral-B Pro-Clinic Sensitive Shield | F88: =20750*CHOOSE(Scenarios!$B$8,Scenarios!$B$3,Scenarios!$C$3,Scenarios!$D$3) -> 20750 | G88: =20750*CHOOSE(Scenarios!$B$8,Scenarios!$B$3,Scenarios!$C$3,Scenarios!$D$3) -> 20750 | H88: =20750*CHOOSE(Scenarios!$B$8,Scenarios!$B$3,Scenarios!$C$3,Scenarios!$D$3) -> 20750 | I88: =20750*CHOOSE(Scenarios!$B$8,Scenarios!$B$3,Scenarios!$C$3,Scenarios!$D$3) -> 20750 | J88: =20750*CHOOSE(Scenarios!$B$8,Scenarios!$B$3,Scenarios!$C$3,Scenarios!$D$3) -> 20750 | K88: =20750*CHOOSE(Scenarios!$B$8,Scenarios!$B$3,Scenarios!$C$3,Scenarios!$D$3) -> 20750 | L88: =20750*CHOOSE(Scenarios!$B$8,Scenarios!$B$3,Scenarios!$C$3,Scenarios!$D$3) -> 20750 | M88: =20750*CHOOSE(Scenarios!$B$8,Scenarios!$B$3,Scenarios!$C$3,Scenarios!$D$3) -> 20750 | ... Q88: =20750*CHOOSE(Scenarios!$B$8,Scenarios!$B$3,Scenarios!$C$3,Scenarios!$D$3) -> 20750 | R88: =SUM(F88:Q88) -> 249000
E89: Oral-B Pro-Clinic Caries Defense | F89: =12500*CHOOSE(Scenarios!$B$8,Scenarios!$B$3,Scenarios!$C$3,Scenarios!$D$3) -> 12500 | G89: =12500*CHOOSE(Scenarios!$B$8,Scenarios!$B$3,Scenarios!$C$3,Scenarios!$D$3) -> 12500 | H89: =12500*CHOOSE(Scenarios!$B$8,Scenarios!$B$3,Scenarios!$C$3,Scenarios!$D$3) -> 12500 | I89: =12500*CHOOSE(Scenarios!$B$8,Scenarios!$B$3,Scenarios!$C$3,Scenarios!$D$3) -> 12500 | J89: =12500*CHOOSE(Scenarios!$B$8,Scenarios!$B$3,Scenarios!$C$3,Scenarios!$D$3) -> 12500 | K89: =12500*CHOOSE(Scenarios!$B$8,Scenarios!$B$3,Scenarios!$C$3,Scenarios!$D$3) -> 12500 | L89: =12500*CHOOSE(Scenarios!$B$8,Scenarios!$B$3,Scenarios!$C$3,Scenarios!$D$3) -> 12500 | M89: =12500*CHOOSE(Scenarios!$B$8,Scenarios!$B$3,Scenarios!$C$3,Scenarios!$D$3) -> 12500 | ... Q89: =12500*CHOOSE(Scenarios!$B$8,Scenarios!$B$3,Scenarios!$C$3,Scenarios!$D$3) -> 12500 | R89: =SUM(F89:Q89) -> 150000
D90: Выручка ( без НДС, тыс. руб ) | E90: Oral-B Pro-Clinic Total Restore | F90: =F87/1000*Assumptions!$Q$19 -> 15979.167 | G90: =G87/1000*Assumptions!$Q$19 -> 15979.167 | H90: =H87/1000*Assumptions!$Q$19 -> 15979.167 | I90: =I87/1000*Assumptions!$Q$19 -> 15979.167 | J90: =J87/1000*Assumptions!$Q$19 -> 15979.167 | K90: =K87/1000*Assumptions!$Q$19 -> 15979.167 | L90: =L87/1000*Assumptions!$Q$19 -> 15979.167 | M90: =M87/1000*Assumptions!$Q$19 -> 15979.167 | ... Q90: =Q87/1000*Assumptions!$Q$19 -> 15979.167 | R90: =SUM(F90:Q90) -> 191750 | T90: BEP | U90: Mean
E91: Oral-B Pro-Clinic Sensitive Shield | F91: =F88/1000*Assumptions!$Q$20 -> 5732.1875 | G91: =G88/1000*Assumptions!$Q$20 -> 5732.1875 | H91: =H88/1000*Assumptions!$Q$20 -> 5732.1875 | I91: =I88/1000*Assumptions!$Q$20 -> 5732.1875 | J91: =J88/1000*Assumptions!$Q$20 -> 5732.1875 | K91: =K88/1000*Assumptions!$Q$20 -> 5732.1875 | L91: =L88/1000*Assumptions!$Q$20 -> 5732.1875 | M91: =M88/1000*Assumptions!$Q$20 -> 5732.1875 | ... Q91: =Q88/1000*Assumptions!$Q$20 -> 5732.1875 | R91: =SUM(F91:Q91) -> 68786.25 | T91: =$R$98/(Assumptions!$M$19-'Стоимость производства'!$H$12) -> 444.87312 | U91: =(T91+T92+T93)/3 -> 488.77929
E92: Oral-B Pro-Clinic Caries Defense | F92: =F89/1000*Assumptions!$Q$21 -> 3385.4167 | G92: =G89/1000*Assumptions!$Q$21 -> 3385.4167 | H92: =H89/1000*Assumptions!$Q$21 -> 3385.4167 | I92: =I89/1000*Assumptions!$Q$21 -> 3385.4167 | J92: =J89/1000*Assumptions!$Q$21 -> 3385.4167 | K92: =K89/1000*Assumptions!$Q$21 -> 3385.4167 | L92: =L89/1000*Assumptions!$Q$21 -> 3385.4167 | M92: =M89/1000*Assumptions!$Q$21 -> 3385.4167 | ... Q92: =Q89/1000*Assumptions!$Q$21 -> 3385.4167 | R92: =SUM(F92:Q92) -> 40625 | T92: =$R$98/(Assumptions!$M$20-'Стоимость производства'!$H$34) -> 547.61609
D93: Прямые расходы (COGS) | E93: Oral-B Pro-Clinic Total Restore | F93: =(F87/1000) * 'Стоимость производства'!$H$12 * 1.06*1.06*1.06 -> 6947.8648 | G93: =(G87/1000) * 'Стоимость производства'!$H$12 * 1.06*1.06*1.06 -> 6947.8648 | H93: =(H87/1000) * 'Стоимость производства'!$H$12 * 1.06*1.06*1.06 -> 6947.8648 | I93: =(I87/1000) * 'Стоимость производства'!$H$12 * 1.06*1.06*1.06 -> 6947.8648 | J93: =(J87/1000) * 'Стоимость производства'!$H$12 * 1.06*1.06*1.06 -> 6947.8648 | K93: =(K87/1000) * 'Стоимость производства'!$H$12 * 1.06*1.06*1.06 -> 6947.8648 | L93: =(L87/1000) * 'Стоимость производства'!$H$12 * 1.06*1.06*1.06 -> 6947.8648 | M93: =(M87/1000) * 'Стоимость производства'!$H$12 * 1.06*1.06*1.06 -> 6947.8648 | ... Q93: =(Q87/1000) * 'Стоимость производства'!$H$12 * 1.06*1.06*1.06 -> 6947.8648 | R93: =SUM(F93:Q93) -> 83374.378 | T93: =$R$98/(Assumptions!$M$21-'Стоимость производства'!$H$61) -> 473.84865
E94: Oral-B Pro-Clinic Sensitive Shield | F94: ='Стоимость производства'!$H$34*'P&L'!F88 /1000* 1.06*1.06*1.06 -> 2903.7298 | G94: ='Стоимость производства'!$H$34*'P&L'!G88 /1000* 1.06*1.06*1.06 -> 2903.7298 | H94: ='Стоимость производства'!$H$34*'P&L'!H88 /1000* 1.06*1.06*1.06 -> 2903.7298 | I94: ='Стоимость производства'!$H$34*'P&L'!I88 /1000* 1.06*1.06*1.06 -> 2903.7298 | J94: ='Стоимость производства'!$H$34*'P&L'!J88 /1000* 1.06*1.06*1.06 -> 2903.7298 | K94: ='Стоимость производства'!$H$34*'P&L'!K88 /1000* 1.06*1.06*1.06 -> 2903.7298 | L94: ='Стоимость производства'!$H$34*'P&L'!L88 /1000* 1.06*1.06*1.06 -> 2903.7298 | M94: ='Стоимость производства'!$H$34*'P&L'!M88 /1000* 1.06*1.06*1.06 -> 2903.7298 | ... Q94: ='Стоимость производства'!$H$34*'P&L'!Q88 /1000* 1.06*1.06*1.06 -> 2903.7298 | R94: =SUM(F94:Q94) -> 34844.758
E95: Oral-B Pro-Clinic Caries Defense | F95: =('Стоимость производства'!$H$61)*'P&L'!F89/1000* 1.06*1.06*1.06 -> 1469.1715 | G95: =('Стоимость производства'!$H$61)*'P&L'!G89/1000* 1.06*1.06*1.06 -> 1469.1715 | H95: =('Стоимость производства'!$H$61)*'P&L'!H89/1000* 1.06*1.06*1.06 -> 1469.1715 | I95: =('Стоимость производства'!$H$61)*'P&L'!I89/1000* 1.06*1.06*1.06 -> 1469.1715 | J95: =('Стоимость производства'!$H$61)*'P&L'!J89/1000* 1.06*1.06*1.06 -> 1469.1715 | K95: =('Стоимость производства'!$H$61)*'P&L'!K89/1000* 1.06*1.06*1.06 -> 1469.1715 | L95: =('Стоимость производства'!$H$61)*'P&L'!L89/1000* 1.06*1.06*1.06 -> 1469.1715 | M95: =('Стоимость производства'!$H$61)*'P&L'!M89/1000* 1.06*1.06*1.06 -> 1469.1715 | ... Q95: =('Стоимость производства'!$H$61)*'P&L'!Q89/1000* 1.06*1.06*1.06 -> 1469.1715 | R95: =SUM(F95:Q95) -> 17630.057
D96: Расходы на продвижение | F96: =Assumptions!$F$32* 1.06*1.06*1.06 -> 2179.5593 | G96: =Assumptions!$F$32* 1.06*1.06*1.06 -> 2179.5593 | H96: =Assumptions!$F$32* 1.06*1.06*1.06 -> 2179.5593 | I96: =Assumptions!$F$32* 1.06*1.06*1.06 -> 2179.5593 | J96: =Assumptions!$F$32* 1.06*1.06*1.06 -> 2179.5593 | K96: =Assumptions!$F$32* 1.06*1.06*1.06 -> 2179.5593 | L96: =Assumptions!$F$32* 1.06*1.06*1.06 -> 2179.5593 | M96: =Assumptions!$F$32* 1.06*1.06*1.06 -> 2179.5593 | ... Q96: =Assumptions!$F$32* 1.06*1.06*1.06 -> 2179.5593 | R96: =SUM(F96:Q96) -> 26154.711
D97: Амортизация | F97: =Assumptions!$B$43 -> 553.80754 | G97: =Assumptions!$B$43 -> 553.80754 | H97: =Assumptions!$B$43 -> 553.80754 | I97: =Assumptions!$B$43 -> 553.80754 | J97: =Assumptions!$B$43 -> 553.80754 | K97: =Assumptions!$B$43 -> 553.80754 | L97: =Assumptions!$B$43 -> 553.80754 | M97: =Assumptions!$B$43 -> 553.80754 | ... Q97: =Assumptions!$B$43 -> 553.80754 | R97: =Q97*12 -> 6645.6905
D98: OPEX | F98: =Assumptions!$F$39* 1.06*1.06*1.06 -> 5514.4041 | G98: =Assumptions!$F$39* 1.06*1.06*1.06 -> 5514.4041 | H98: =Assumptions!$F$39* 1.06*1.06*1.06 -> 5514.4041 | I98: =Assumptions!$F$39* 1.06*1.06*1.06 -> 5514.4041 | J98: =Assumptions!$F$39* 1.06*1.06*1.06 -> 5514.4041 | K98: =Assumptions!$F$39* 1.06*1.06*1.06 -> 5514.4041 | L98: =Assumptions!$F$39* 1.06*1.06*1.06 -> 5514.4041 | M98: =Assumptions!$F$39* 1.06*1.06*1.06 -> 5514.4041 | ... Q98: =Assumptions!$F$39* 1.06*1.06*1.06 -> 5514.4041 | R98: =SUM(F98:Q98) -> 66172.849
D99: EBIT | F99: =SUM(F100:F102) - F98 - F97 -> 7707.7931 | G99: =SUM(G100:G102) - G98 - G97 -> 7707.7931 | H99: =SUM(H100:H102) - H98 - H97 -> 7707.7931 | I99: =SUM(I100:I102) - I98 - I97 -> 7707.7931 | J99: =SUM(J100:J102) - J98 - J97 -> 7707.7931 | K99: =SUM(K100:K102) - K98 - K97 -> 7707.7931 | L99: =SUM(L100:L102) - L98 - L97 -> 7707.7931 | M99: =SUM(M100:M102) - M98 - M97 -> 7707.7931 | ... R99: =SUM(R100:R102) - R98 - R97 -> 92493.517
D100: Маржинальная прибыль | E100: Oral-B Pro-Clinic Total Restore | F100: =F90-F93 -> 9031.3019 | G100: =G90-G93 -> 9031.3019 | H100: =H90-H93 -> 9031.3019 | I100: =I90-I93 -> 9031.3019 | J100: =J90-J93 -> 9031.3019 | K100: =K90-K93 -> 9031.3019 | L100: =L90-L93 -> 9031.3019 | M100: =M90-M93 -> 9031.3019 | ... Q100: =Q90-Q93 -> 9031.3019 | R100: =SUM(F100:Q100) -> 108375.62
E101: Oral-B Pro-Clinic Sensitive Shield | F101: =F91-F94 -> 2828.4577 | G101: =G91-G94 -> 2828.4577 | H101: =H91-H94 -> 2828.4577 | I101: =I91-I94 -> 2828.4577 | J101: =J91-J94 -> 2828.4577 | K101: =K91-K94 -> 2828.4577 | L101: =L91-L94 -> 2828.4577 | M101: =M91-M94 -> 2828.4577 | ... Q101: =Q91-Q94 -> 2828.4577 | R101: =SUM(F101:Q101) -> 33941.492
E102: Oral-B Pro-Clinic Caries Defense | F102: =F92-F95 -> 1916.2452 | G102: =G92-G95 -> 1916.2452 | H102: =H92-H95 -> 1916.2452 | I102: =I92-I95 -> 1916.2452 | J102: =J92-J95 -> 1916.2452 | K102: =K92-K95 -> 1916.2452 | L102: =L92-L95 -> 1916.2452 | M102: =M92-M95 -> 1916.2452 | ... Q102: =Q92-Q95 -> 1916.2452 | R102: =SUM(F102:Q102) -> 22994.943
D103: EBITDA | F103: =F105+F104+F97 -> 8261.6007 | G103: =G105+G104+G97 -> 8261.6007 | H103: =H105+H104+H97 -> 8261.6007 | I103: =I105+I104+I97 -> 8261.6007 | J103: =J105+J104+J97 -> 8261.6007 | K103: =K105+K104+K97 -> 8261.6007 | L103: =L105+L104+L97 -> 8261.6007 | M103: =M105+M104+M97 -> 8261.6007 | ... Q103: =Q105+Q104+Q97 -> 8261.6007 | R103: =SUM(F103:Q103) -> 99139.208
D104: Налог на прибыль | F104: =MAX(0,F99*Assumptions!$B$10) -> 1926.9483 | G104: =MAX(0,G99*Assumptions!$B$10) -> 1926.9483 | H104: =MAX(0,H99*Assumptions!$B$10) -> 1926.9483 | I104: =MAX(0,I99*Assumptions!$B$10) -> 1926.9483 | J104: =MAX(0,J99*Assumptions!$B$10) -> 1926.9483 | K104: =MAX(0,K99*Assumptions!$B$10) -> 1926.9483 | L104: =MAX(0,L99*Assumptions!$B$10) -> 1926.9483 | M104: =MAX(0,M99*Assumptions!$B$10) -> 1926.9483 | ... Q104: =MAX(0,Q99*Assumptions!$B$10) -> 1926.9483 | R104: =SUM(F104:Q104) -> 23123.379
D105: Net Profit | F105: =F99-F104 -> 5780.8448 | G105: =G99-G104 -> 5780.8448 | H105: =H99-H104 -> 5780.8448 | I105: =I99-I104 -> 5780.8448 | J105: =J99-J104 -> 5780.8448 | K105: =K99-K104 -> 5780.8448 | L105: =L99-L104 -> 5780.8448 | M105: =M99-M104 -> 5780.8448 | ... Q105: =Q99-Q104 -> 5780.8448 | R105: =SUM(F105:Q105) -> 69370.138
D111: Прогноз на 2031 год
F112: 46023 | G112: 46054 | H112: 46082 | I112: 46113 | J112: 46143 | K112: 46174 | L112: 46204 | M112: 46235 | N112: 46266 | O112: 46296 | P112: 46327 | Q112: 46357 | R112: Итог
D113: Объем продаж | E113: Oral-B Pro-Clinic Total Restore | F113: =50000*CHOOSE(Scenarios!$B$8,Scenarios!$B$3,Scenarios!$C$3,Scenarios!$D$3) -> 50000 | G113: =50000*CHOOSE(Scenarios!$B$8,Scenarios!$B$3,Scenarios!$C$3,Scenarios!$D$3) -> 50000 | H113: =50000*CHOOSE(Scenarios!$B$8,Scenarios!$B$3,Scenarios!$C$3,Scenarios!$D$3) -> 50000 | I113: =50000*CHOOSE(Scenarios!$B$8,Scenarios!$B$3,Scenarios!$C$3,Scenarios!$D$3) -> 50000 | J113: =50000*CHOOSE(Scenarios!$B$8,Scenarios!$B$3,Scenarios!$C$3,Scenarios!$D$3) -> 50000 | K113: =50000*CHOOSE(Scenarios!$B$8,Scenarios!$B$3,Scenarios!$C$3,Scenarios!$D$3) -> 50000 | L113: =50000*CHOOSE(Scenarios!$B$8,Scenarios!$B$3,Scenarios!$C$3,Scenarios!$D$3) -> 50000 | M113: =50000*CHOOSE(Scenarios!$B$8,Scenarios!$B$3,Scenarios!$C$3,Scenarios!$D$3) -> 50000 | ... Q113: =50000*CHOOSE(Scenarios!$B$8,Scenarios!$B$3,Scenarios!$C$3,Scenarios!$D$3) -> 50000 | R113: =SUM(F113:Q113) -> 600000
E114: Oral-B Pro-Clinic Sensitive Shield | F114: =20750*CHOOSE(Scenarios!$B$8,Scenarios!$B$3,Scenarios!$C$3,Scenarios!$D$3) -> 20750 | G114: =20750*CHOOSE(Scenarios!$B$8,Scenarios!$B$3,Scenarios!$C$3,Scenarios!$D$3) -> 20750 | H114: =20750*CHOOSE(Scenarios!$B$8,Scenarios!$B$3,Scenarios!$C$3,Scenarios!$D$3) -> 20750 | I114: =20750*CHOOSE(Scenarios!$B$8,Scenarios!$B$3,Scenarios!$C$3,Scenarios!$D$3) -> 20750 | J114: =20750*CHOOSE(Scenarios!$B$8,Scenarios!$B$3,Scenarios!$C$3,Scenarios!$D$3) -> 20750 | K114: =20750*CHOOSE(Scenarios!$B$8,Scenarios!$B$3,Scenarios!$C$3,Scenarios!$D$3) -> 20750 | L114: =20750*CHOOSE(Scenarios!$B$8,Scenarios!$B$3,Scenarios!$C$3,Scenarios!$D$3) -> 20750 | M114: =20750*CHOOSE(Scenarios!$B$8,Scenarios!$B$3,Scenarios!$C$3,Scenarios!$D$3) -> 20750 | ... Q114: =20750*CHOOSE(Scenarios!$B$8,Scenarios!$B$3,Scenarios!$C$3,Scenarios!$D$3) -> 20750 | R114: =SUM(F114:Q114) -> 249000
E115: Oral-B Pro-Clinic Caries Defense | F115: =12500*CHOOSE(Scenarios!$B$8,Scenarios!$B$3,Scenarios!$C$3,Scenarios!$D$3) -> 12500 | G115: =12500*CHOOSE(Scenarios!$B$8,Scenarios!$B$3,Scenarios!$C$3,Scenarios!$D$3) -> 12500 | H115: =12500*CHOOSE(Scenarios!$B$8,Scenarios!$B$3,Scenarios!$C$3,Scenarios!$D$3) -> 12500 | I115: =12500*CHOOSE(Scenarios!$B$8,Scenarios!$B$3,Scenarios!$C$3,Scenarios!$D$3) -> 12500 | J115: =12500*CHOOSE(Scenarios!$B$8,Scenarios!$B$3,Scenarios!$C$3,Scenarios!$D$3) -> 12500 | K115: =12500*CHOOSE(Scenarios!$B$8,Scenarios!$B$3,Scenarios!$C$3,Scenarios!$D$3) -> 12500 | L115: =12500*CHOOSE(Scenarios!$B$8,Scenarios!$B$3,Scenarios!$C$3,Scenarios!$D$3) -> 12500 | M115: =12500*CHOOSE(Scenarios!$B$8,Scenarios!$B$3,Scenarios!$C$3,Scenarios!$D$3) -> 12500 | ... Q115: =12500*CHOOSE(Scenarios!$B$8,Scenarios!$B$3,Scenarios!$C$3,Scenarios!$D$3) -> 12500 | R115: =SUM(F115:Q115) -> 150000
D116: Выручка ( без НДС, тыс. руб ) | E116: Oral-B Pro-Clinic Total Restore | F116: =F113/1000*Assumptions!$Q$19 -> 15979.167 | G116: =G113/1000*Assumptions!$Q$19 -> 15979.167 | H116: =H113/1000*Assumptions!$Q$19 -> 15979.167 | I116: =I113/1000*Assumptions!$Q$19 -> 15979.167 | J116: =J113/1000*Assumptions!$Q$19 -> 15979.167 | K116: =K113/1000*Assumptions!$Q$19 -> 15979.167 | L116: =L113/1000*Assumptions!$Q$19 -> 15979.167 | M116: =M113/1000*Assumptions!$Q$19 -> 15979.167 | ... Q116: =Q113/1000*Assumptions!$Q$19 -> 15979.167 | R116: =SUM(F116:Q116) -> 191750
E117: Oral-B Pro-Clinic Sensitive Shield | F117: =F114/1000*Assumptions!$Q$20 -> 5732.1875 | G117: =G114/1000*Assumptions!$Q$20 -> 5732.1875 | H117: =H114/1000*Assumptions!$Q$20 -> 5732.1875 | I117: =I114/1000*Assumptions!$Q$20 -> 5732.1875 | J117: =J114/1000*Assumptions!$Q$20 -> 5732.1875 | K117: =K114/1000*Assumptions!$Q$20 -> 5732.1875 | L117: =L114/1000*Assumptions!$Q$20 -> 5732.1875 | M117: =M114/1000*Assumptions!$Q$20 -> 5732.1875 | ... Q117: =Q114/1000*Assumptions!$Q$20 -> 5732.1875 | R117: =SUM(F117:Q117) -> 68786.25
E118: Oral-B Pro-Clinic Caries Defense | F118: =F115/1000*Assumptions!$Q$21 -> 3385.4167 | G118: =G115/1000*Assumptions!$Q$21 -> 3385.4167 | H118: =H115/1000*Assumptions!$Q$21 -> 3385.4167 | I118: =I115/1000*Assumptions!$Q$21 -> 3385.4167 | J118: =J115/1000*Assumptions!$Q$21 -> 3385.4167 | K118: =K115/1000*Assumptions!$Q$21 -> 3385.4167 | L118: =L115/1000*Assumptions!$Q$21 -> 3385.4167 | M118: =M115/1000*Assumptions!$Q$21 -> 3385.4167 | ... Q118: =Q115/1000*Assumptions!$Q$21 -> 3385.4167 | R118: =SUM(F118:Q118) -> 40625
D119: Прямые расходы (COGS) | E119: Oral-B Pro-Clinic Total Restore | F119: =(F113/1000) * 'Стоимость производства'!$H$12* 1.06*1.06*1.06*1.06 -> 7364.7367 | G119: =(G113/1000) * 'Стоимость производства'!$H$12* 1.06*1.06*1.06*1.06 -> 7364.7367 | H119: =(H113/1000) * 'Стоимость производства'!$H$12* 1.06*1.06*1.06*1.06 -> 7364.7367 | I119: =(I113/1000) * 'Стоимость производства'!$H$12* 1.06*1.06*1.06*1.06 -> 7364.7367 | J119: =(J113/1000) * 'Стоимость производства'!$H$12* 1.06*1.06*1.06*1.06 -> 7364.7367 | K119: =(K113/1000) * 'Стоимость производства'!$H$12* 1.06*1.06*1.06*1.06 -> 7364.7367 | L119: =(L113/1000) * 'Стоимость производства'!$H$12* 1.06*1.06*1.06*1.06 -> 7364.7367 | M119: =(M113/1000) * 'Стоимость производства'!$H$12* 1.06*1.06*1.06*1.06 -> 7364.7367 | ... Q119: =(Q113/1000) * 'Стоимость производства'!$H$12* 1.06*1.06*1.06*1.06 -> 7364.7367 | R119: =SUM(F119:Q119) -> 88376.84
E120: Oral-B Pro-Clinic Sensitive Shield | F120: ='Стоимость производства'!$H$34*'P&L'!F114 /1000* 1.06*1.06*1.06*1.06 -> 3077.9536 | G120: ='Стоимость производства'!$H$34*'P&L'!G114 /1000* 1.06*1.06*1.06*1.06 -> 3077.9536 | H120: ='Стоимость производства'!$H$34*'P&L'!H114 /1000* 1.06*1.06*1.06*1.06 -> 3077.9536 | I120: ='Стоимость производства'!$H$34*'P&L'!I114 /1000* 1.06*1.06*1.06*1.06 -> 3077.9536 | J120: ='Стоимость производства'!$H$34*'P&L'!J114 /1000* 1.06*1.06*1.06*1.06 -> 3077.9536 | K120: ='Стоимость производства'!$H$34*'P&L'!K114 /1000* 1.06*1.06*1.06*1.06 -> 3077.9536 | L120: ='Стоимость производства'!$H$34*'P&L'!L114 /1000* 1.06*1.06*1.06*1.06 -> 3077.9536 | M120: ='Стоимость производства'!$H$34*'P&L'!M114 /1000* 1.06*1.06*1.06*1.06 -> 3077.9536 | ... Q120: ='Стоимость производства'!$H$34*'P&L'!Q114 /1000* 1.06*1.06*1.06*1.06 -> 3077.9536 | R120: =SUM(F120:Q120) -> 36935.443
E121: Oral-B Pro-Clinic Caries Defense | F121: =('Стоимость производства'!$H$61)*'P&L'!F115/1000* 1.06*1.06*1.06*1.06 -> 1557.3217 | G121: =('Стоимость производства'!$H$61)*'P&L'!G115/1000* 1.06*1.06*1.06*1.06 -> 1557.3217 | H121: =('Стоимость производства'!$H$61)*'P&L'!H115/1000* 1.06*1.06*1.06*1.06 -> 1557.3217 | I121: =('Стоимость производства'!$H$61)*'P&L'!I115/1000* 1.06*1.06*1.06*1.06 -> 1557.3217 | J121: =('Стоимость производства'!$H$61)*'P&L'!J115/1000* 1.06*1.06*1.06*1.06 -> 1557.3217 | K121: =('Стоимость производства'!$H$61)*'P&L'!K115/1000* 1.06*1.06*1.06*1.06 -> 1557.3217 | L121: =('Стоимость производства'!$H$61)*'P&L'!L115/1000* 1.06*1.06*1.06*1.06 -> 1557.3217 | M121: =('Стоимость производства'!$H$61)*'P&L'!M115/1000* 1.06*1.06*1.06*1.06 -> 1557.3217 | ... Q121: =('Стоимость производства'!$H$61)*'P&L'!Q115/1000* 1.06*1.06*1.06*1.06 -> 1557.3217 | R121: =SUM(F121:Q121) -> 18687.861
D122: Расходы на продвижение | F122: =Assumptions!$G$32* 1.06*1.06*1.06*1.06 -> 2272.4585 | G122: =Assumptions!$G$32* 1.06*1.06*1.06*1.06 -> 2272.4585 | H122: =Assumptions!$G$32* 1.06*1.06*1.06*1.06 -> 2272.4585 | I122: =Assumptions!$G$32* 1.06*1.06*1.06*1.06 -> 2272.4585 | J122: =Assumptions!$G$32* 1.06*1.06*1.06*1.06 -> 2272.4585 | K122: =Assumptions!$G$32* 1.06*1.06*1.06*1.06 -> 2272.4585 | L122: =Assumptions!$G$32* 1.06*1.06*1.06*1.06 -> 2272.4585 | M122: =Assumptions!$G$32* 1.06*1.06*1.06*1.06 -> 2272.4585 | ... Q122: =Assumptions!$G$32* 1.06*1.06*1.06*1.06 -> 2272.4585 | R122: =SUM(F122:Q122) -> 27269.502
D123: Амортизация | F123: =Assumptions!$B$43 -> 553.80754 | G123: =Assumptions!$B$43 -> 553.80754 | H123: =Assumptions!$B$43 -> 553.80754 | I123: =Assumptions!$B$43 -> 553.80754 | J123: =Assumptions!$B$43 -> 553.80754 | K123: =Assumptions!$B$43 -> 553.80754 | L123: =Assumptions!$B$43 -> 553.80754 | M123: =Assumptions!$B$43 -> 553.80754 | ... Q123: =Assumptions!$B$43 -> 553.80754 | R123: =Q123*12 -> 6645.6905
D124: OPEX | F124: =Assumptions!$F$40* 1.06*1.06*1.06*1.06 -> 5239.2794 | G124: =Assumptions!$F$40* 1.06*1.06*1.06*1.06 -> 5239.2794 | H124: =Assumptions!$F$40* 1.06*1.06*1.06*1.06 -> 5239.2794 | I124: =Assumptions!$F$40* 1.06*1.06*1.06*1.06 -> 5239.2794 | J124: =Assumptions!$F$40* 1.06*1.06*1.06*1.06 -> 5239.2794 | K124: =Assumptions!$F$40* 1.06*1.06*1.06*1.06 -> 5239.2794 | L124: =Assumptions!$F$40* 1.06*1.06*1.06*1.06 -> 5239.2794 | M124: =Assumptions!$F$40* 1.06*1.06*1.06*1.06 -> 5239.2794 | ... Q124: =Assumptions!$F$40* 1.06*1.06*1.06*1.06 -> 5239.2794 | R124: =SUM(F124:Q124) -> 62871.353
D125: EBIT | F125: =SUM(F126:F128) - F124 - F123 -> 7303.6718 | G125: =SUM(G126:G128) - G124 - G123 -> 7303.6718 | H125: =SUM(H126:H128) - H124 - H123 -> 7303.6718 | I125: =SUM(I126:I128) - I124 - I123 -> 7303.6718 | J125: =SUM(J126:J128) - J124 - J123 -> 7303.6718 | K125: =SUM(K126:K128) - K124 - K123 -> 7303.6718 | L125: =SUM(L126:L128) - L124 - L123 -> 7303.6718 | M125: =SUM(M126:M128) - M124 - M123 -> 7303.6718 | ... R125: =SUM(R126:R128) - R124 - R123 -> 87644.062
D126: Маржинальная прибыль | E126: Oral-B Pro-Clinic Total Restore | F126: =F116-F119 -> 8614.43 | G126: =G116-G119 -> 8614.43 | H126: =H116-H119 -> 8614.43 | I126: =I116-I119 -> 8614.43 | J126: =J116-J119 -> 8614.43 | K126: =K116-K119 -> 8614.43 | L126: =L116-L119 -> 8614.43 | M126: =M116-M119 -> 8614.43 | ... Q126: =Q116-Q119 -> 8614.43 | R126: =SUM(F126:Q126) -> 103373.16
...

Sheet Investment Analysis
B4: Прогноз на 2027 год | Q4: NWC | R4: =R8/365 -> 0.16438356
B5: Дата | C5: 46023 | D5: 46054 | E5: 46082 | F5: 46113 | G5: 46143 | H5: 46174 | I5: 46204 | J5: 46235 | K5: 46266 | L5: 46296 | M5: 46327 | N5: 46357 | Q5: WACC | R5: =0.205+CHOOSE(Scenarios!B8,Scenarios!B5,Scenarios!C5,Scenarios!D5) -> 0.205 | S5: =(1+R5)^(1/12) -> 1.0156613
B6: Net Profit | C6: ='P&L'!F27 -> -2375.7228 | D6: ='P&L'!G27 -> -971.68046 | E6: ='P&L'!H27 -> 324.27142 | F6: ='P&L'!I27 -> 1377.3032 | G6: ='P&L'!J27 -> 1903.8191 | H6: ='P&L'!K27 -> 2430.335 | I6: ='P&L'!L27 -> 2430.335 | J6: ='P&L'!M27 -> 2956.8508 | ... N6: ='P&L'!Q27 -> 3483.3667 | Q6: CAPEX (тыс. руб) | R6: =Assumptions!B42*CHOOSE(Scenarios!B8,Scenarios!B4,Scenarios!C4,Scenarios!D4) -> 85049
B7: Амортизация | C7: {='P&L'!F19:Q19} -> 553.80754 | D7: 553.80754 | E7: 553.80754 | F7: 553.80754 | G7: 553.80754 | H7: 553.80754 | I7: 553.80754 | J7: 553.80754 | K7: 553.80754 | L7: 553.80754 | M7: 553.80754 | N7: 553.80754 | Q7: NPV (тыс. руб) | R7: =SUM(C13:N13) + SUM(C26:N26) +SUM(C39:N39) +SUM(C52:N52) +SUM(C64:N64) -> 89645.615
B8: Общая выручка | C8: =SUM('P&L'!F12:F14) -> 5091.6667 | D8: =SUM('P&L'!G12:G14) -> 7637.5 | E8: =SUM('P&L'!H12:H14) -> 10183.333 | F8: =SUM('P&L'!I12:I14) -> 12729.167 | G8: =SUM('P&L'!J12:J14) -> 14002.083 | H8: =SUM('P&L'!K12:K14) -> 15275 | I8: =SUM('P&L'!L12:L14) -> 15275 | J8: =SUM('P&L'!M12:M14) -> 16547.917 | ... N8: =SUM('P&L'!Q12:Q14) -> 17820.833 | Q8: CCC | R8: 60
B9: ΔNWC | D9: =(D8-C8)*$R$4 -> 418.49315 | E9: =(E8-D8)*$R$4 -> 418.49315 | F9: =(F8-E8)*$R$4 -> 418.49315 | G9: =(G8-F8)*$R$4 -> 209.24658 | H9: =(H8-G8)*$R$4 -> 209.24658 | I9: =(I8-H8)*$R$4 -> 0 | J9: =(J8-I8)*$R$4 -> 209.24658 | K9: =(K8-J8)*$R$4 -> 0 | ... N9: =(N8-M8)*$R$4 -> 0 | Q9: IRR | R9: =IRR(Q16:V16) -> 0.50123118
B10: FCFF | C10: =C6+C7-C9-R6 -> -86870.915 | D10: =D6+D7-D9 -> -836.36607 | E10: =E6+E7-E9 -> 459.58581 | F10: =F6+F7-F9 -> 1512.6176 | G10: =G6+G7-G9 -> 2248.38 | H10: =H6+H7-H9 -> 2774.8959 | I10: =I6+I7-I9 -> 2984.1425 | J10: =J6+J7-J9 -> 3301.4118 | K10: =K6+K7-K9 -> 3510.6584 | ... N10: =N6+N7-N9 -> 4037.1743 | Q10: DPP | R10: 30
B11: Cumulative FCFF | C11: =C10 -> -86870.915 | D11: =D10+C11 -> -87707.281 | E11: =E10+D11 -> -87247.696 | F11: =F10+E11 -> -85735.078 | G11: =G10+F11 -> -83486.698 | H11: =H10+G11 -> -80711.802 | I11: =I10+H11 -> -77727.66 | J11: =J10+I11 -> -74426.248 | K11: =K10+J11 -> -70915.589 | ... N11: =N10+M11 -> -59539.829
B12: Коэф. дисконтирования | C12: =$S$5^(COLUMN()-2) -> 1.0156613 | D12: =$S$5^(COLUMN()-2) -> 1.031568 | E12: =$S$5^(COLUMN()-2) -> 1.0477237 | F12: =$S$5^(COLUMN()-2) -> 1.0641324 | G12: =$S$5^(COLUMN()-2) -> 1.0807982 | H12: =$S$5^(COLUMN()-2) -> 1.0977249 | I12: =$S$5^(COLUMN()-2) -> 1.1149168 | J12: =$S$5^(COLUMN()-2) -> 1.1323778 | ... N12: =$S$5^(COLUMN()-2) -> 1.205 | Q12: PP | R12: 25
B13: DCF | C13: =C10/C12 -> -85531.38 | D13: =D10/D12 -> -810.77167 | E13: =E10/E12 -> 438.65173 | F13: =F10/F12 -> 1421.4561 | G13: =G10/G12 -> 2080.2959 | H13: =H10/H12 -> 2527.8609 | I13: =I10/I12 -> 2676.5608 | J13: =J10/J12 -> 2915.4684 | ... N13: =N10/N12 -> 3350.3521
B14: Cumulative DCF | C14: =C13 -> -85531.38 | D14: =D13+C14 -> -86342.151 | E14: =E13+D14 -> -85903.499 | F14: =F13+E14 -> -84482.043 | G14: =G13+F14 -> -82401.747 | H14: =H13+G14 -> -79873.886 | I14: =I13+H14 -> -77197.326 | J14: =J13+I14 -> -74281.857 | K14: =K13+J14 -> -71229.409 | ... N14: =N13+M14 -> -61647.222
P15: Год | Q15: 2026 (CAPEX) | R15: 2027 | S15: 2028 | T15: 2029 | U15: 2030 | V15: 2031
P16: Агрегированные свободные денежным потоки | Q16: =-R6 -> -85049 | R16: =SUM(C10:N10) + R6 -> 25509.171 | S16: =SUM(C23:N23) -> 58489.163 | T16: =SUM(C36:N36) -> 59994.752 | U16: =SUM(C49:N49) -> 75574.63 | V16: =SUM(C61:N61) -> 72378.737
B17: Прогноз на 2028 год
B18: Дата | C18: 46023 | D18: 46054 | E18: 46082 | F18: 46113 | G18: 46143 | H18: 46174 | I18: 46204 | J18: 46235 | K18: 46266 | L18: 46296 | M18: 46327 | N18: 46357
B19: Net Profit | C19: ='P&L'!F53 -> 3792.8852 | D19: ='P&L'!G53 -> 3902.6053 | E19: ='P&L'!H53 -> 4012.3255 | F19: ='P&L'!I53 -> 4122.0456 | G19: ='P&L'!J53 -> 4231.7658 | H19: ='P&L'!K53 -> 4341.4859 | I19: ='P&L'!L53 -> 4451.206 | J19: ='P&L'!M53 -> 4560.9262 | ... N19: ='P&L'!Q53 -> 4895.4476
B20: Амортизация | C20: =C7 -> 553.80754 | D20: =D7 -> 553.80754 | E20: =E7 -> 553.80754 | F20: =F7 -> 553.80754 | G20: =G7 -> 553.80754 | H20: =H7 -> 553.80754 | I20: =I7 -> 553.80754 | J20: =J7 -> 553.80754 | ... N20: =N7 -> 553.80754
B21: Общая выручка | C21: =SUM('P&L'!F38:F40) -> 19110 | D21: =SUM('P&L'!G38:G40) -> 19375.417 | E21: =SUM('P&L'!H38:H40) -> 19640.833 | F21: =SUM('P&L'!I38:I40) -> 19906.25 | G21: =SUM('P&L'!J38:J40) -> 20171.667 | H21: =SUM('P&L'!K38:K40) -> 20437.083 | I21: =SUM('P&L'!L38:L40) -> 20702.5 | J21: =SUM('P&L'!M38:M40) -> 20967.917 | ... N21: =SUM('P&L'!Q38:Q40) -> 21785.833 | Q21: NPV neg | R21: NPV base | S21: NPV pos | X21: Негативный сценарий | Y21: Позитицный сценарий
B22: ΔNWC | C22: =(C21-N8)*$R$4 -> 211.91781 | D22: =(D21-C21)*$R$4 -> 43.630137 | E22: =(E21-D21)*$R$4 -> 43.630137 | F22: =(F21-E21)*$R$4 -> 43.630137 | G22: =(G21-F21)*$R$4 -> 43.630137 | H22: =(H21-G21)*$R$4 -> 43.630137 | I22: =(I21-H21)*$R$4 -> 43.630137 | J22: =(J21-I21)*$R$4 -> 43.630137 | K22: =(K21-J21)*$R$4 -> 33.613014 | ... N22: =(N21-M21)*$R$4 -> 33.613014
B23: FCFF | C23: =C19+C20-C22 -> 4134.7749 | D23: =D19+D20-D22 -> 4412.7827 | E23: =E19+E20-E22 -> 4522.5029 | F23: =F19+F20-F22 -> 4632.223 | G23: =G19+G20-G22 -> 4741.9432 | H23: =H19+H20-H22 -> 4851.6633 | I23: =I19+I20-I22 -> 4961.3834 | J23: =J19+J20-J22 -> 5071.1036 | ... N23: =N19+N20-N22 -> 5415.6422 | P23: Volume +- (10%) | Q23: 57.95 | R23: 89.64 | S23: 100.74 | X23: -31.69 | Y23: 11.1
B24: Cumulative FCFF | C24: =N11+C23 -> -55405.054 | D24: =C24+D23 -> -50992.271 | E24: =D24+E23 -> -46469.768 | F24: =E24+F23 -> -41837.545 | G24: =F24+G23 -> -37095.602 | H24: =G24+H23 -> -32243.939 | I24: =H24+I23 -> -27282.556 | J24: =I24+J23 -> -22211.452 | K24: =J24+K23 -> -17046.701 | ... N24: =M24+N23 -> -1050.6655
B25: Коэф. дисконтирования | C25: =$S$5^(COLUMN()+12-2) -> 1.2238719 | D25: =$S$5^(COLUMN()+12-2) -> 1.2430394 | E25: =$S$5^(COLUMN()+12-2) -> 1.262507 | F25: =$S$5^(COLUMN()+12-2) -> 1.2822796 | G25: =$S$5^(COLUMN()+12-2) -> 1.3023618 | H25: =$S$5^(COLUMN()+12-2) -> 1.3227585 | I25: =$S$5^(COLUMN()+12-2) -> 1.3434747 | J25: =$S$5^(COLUMN()+12-2) -> 1.3645153 | ... N25: =$S$5^(COLUMN()+12-2) -> 1.452025 | P25: CAPEX (+-10%) | Q25: 81.2 | R25: 89.64 | S25: 98 | X25: -27.21 | Y25: 27.21
B26: DCF | C26: =C23/C25 -> 3378.4376 | D26: =D23/D25 -> 3549.9943 | E26: =E23/E25 -> 3582.1605 | F26: =F23/F25 -> 3612.4906 | G26: =G23/G25 -> 3641.0337 | H26: =H23/H25 -> 3667.8375 | I26: =I23/I25 -> 3692.9489 | J26: =J23/J25 -> 3716.4138 | ... N26: =N23/N25 -> 3729.7169 | P26: COGS (+-10%) | Q26: 62.43 | R26: 89.64 | S26: 116.85 | X26: -14.84 | Y26: 14.76
B27: Cumulative DCF | C27: =N14+C26 -> -58268.785 | D27: =D26+C27 -> -54718.79 | E27: =E26+D27 -> -51136.63 | F27: =F26+E27 -> -47524.139 | G27: =G26+F27 -> -43883.106 | H27: =H26+G27 -> -40215.268 | I27: =I26+H27 -> -36522.319 | J27: =J26+I27 -> -32805.905 | K27: =K26+J27 -> -29079.226 | ... N27: =N26+M27 -> -17891.249
P28: WACC (+-2п.п.) | Q28: 82.4 | R28: 89.64 | S28: 97.4 | X28: -8.44 | Y28: 8.36
P29: OPEX (+-10%) | Q29: 74.8 | R29: 89.64 | S29: 104.4 | X29: -7.24 | Y29: 7.76
B30: Прогноз на 2029 год
B31: Дата | C31: 46023 | D31: 46054 | E31: 46082 | F31: 46113 | G31: 46143 | H31: 46174 | I31: 46204 | J31: 46235 | K31: 46266 | L31: 46296 | M31: 46327 | N31: 46357
B32: Net Profit | C32: ='P&L'!F79 -> 4313.18 | D32: ='P&L'!G79 -> 4369.6456 | E32: ='P&L'!H79 -> 4426.1111 | F32: ='P&L'!I79 -> 4482.5767 | G32: ='P&L'!J79 -> 4482.5767 | H32: ='P&L'!K79 -> 4482.5767 | I32: ='P&L'!L79 -> 4482.5767 | J32: ='P&L'!M79 -> 4482.5767 | ... N32: ='P&L'!Q79 -> 4482.5767
B33: Амортизация | C33: =C20 -> 553.80754 | D33: =D20 -> 553.80754 | E33: =E20 -> 553.80754 | F33: =F20 -> 553.80754 | G33: =G20 -> 553.80754 | H33: =H20 -> 553.80754 | I33: =I20 -> 553.80754 | J33: =J20 -> 553.80754 | ... N33: =N20 -> 553.80754
B34: Общая выручка | C34: =SUM('P&L'!F64:F66) -> 21990.312 | D34: =SUM('P&L'!G64:G66) -> 22131.146 | E34: =SUM('P&L'!H64:H66) -> 22271.979 | F34: =SUM('P&L'!I64:I66) -> 22412.812 | G34: =SUM('P&L'!J64:J66) -> 22412.812 | H34: =SUM('P&L'!K64:K66) -> 22412.812 | I34: =SUM('P&L'!L64:L66) -> 22412.812 | J34: =SUM('P&L'!M64:M66) -> 22412.812 | ... N34: =SUM('P&L'!Q64:Q66) -> 22412.812
B35: ΔNWC | C35: =(C34-N21)*$R$4 -> 33.613014 | D35: =(D34-C34)*$R$4 -> 23.150685 | E35: =(E34-D34)*$R$4 -> 23.150685 | F35: =(F34-E34)*$R$4 -> 23.150685 | G35: =(G34-F34)*$R$4 -> 0 | H35: =(H34-G34)*$R$4 -> 0 | I35: =(I34-H34)*$R$4 -> 0 | J35: =(J34-I34)*$R$4 -> 0 | K35: =(K34-J34)*$R$4 -> 0 | ... N35: =(N34-M34)*$R$4 -> 0
B36: FCFF | C36: =C32+C33-C35 -> 4833.3745 | D36: =D32+D33-D35 -> 4900.3024 | E36: =E32+E33-E35 -> 4956.768 | F36: =F32+F33-F35 -> 5013.2336 | G36: =G32+G33-G35 -> 5036.3842 | H36: =H32+H33-H35 -> 5036.3842 | I36: =I32+I33-I35 -> 5036.3842 | J36: =J32+J33-J35 -> 5036.3842 | ... N36: =N32+N33-N35 -> 5036.3842
B37: Cumulative FCFF | C37: =C36+N24 -> 3782.709 | D37: =D36+C37 -> 8683.0114 | E37: =E36+D37 -> 13639.779 | F37: =F36+E37 -> 18653.013 | G37: =G36+F37 -> 23689.397 | H37: =H36+G37 -> 28725.781 | I37: =I36+H37 -> 33762.166 | J37: =J36+I37 -> 38798.55 | K37: =K36+J37 -> 43834.934 | ... N37: =N36+M37 -> 58944.087
B38: Коэф. дисконтирования | C38: =$S$5^(COLUMN()+24-2) -> 1.4747657 | D38: =$S$5^(COLUMN()+24-2) -> 1.4978625 | E38: =$S$5^(COLUMN()+24-2) -> 1.521321 | F38: =$S$5^(COLUMN()+24-2) -> 1.5451469 | G38: =$S$5^(COLUMN()+24-2) -> 1.569346 | H38: =$S$5^(COLUMN()+24-2) -> 1.593924 | I38: =$S$5^(COLUMN()+24-2) -> 1.618887 | J38: =$S$5^(COLUMN()+24-2) -> 1.6442409 | ... N38: =$S$5^(COLUMN()+24-2) -> 1.7496901
B39: DCF | C39: =C36/C38 -> 3277.3848 | D39: =D36/D38 -> 3271.5303 | E39: =E36/E38 -> 3258.2 | F39: =F36/F38 -> 3244.5029 | G39: =G36/G38 -> 3209.225 | H39: =H36/H38 -> 3159.7392 | I39: =I36/I38 -> 3111.0165 | J39: =J36/J38 -> 3063.0452 | ... N39: =N36/N38 -> 2878.4435
B40: Cumulative DCF | C40: =N27+C39 -> -14613.864 | D40: =D39+C40 -> -11342.334 | E40: =E39+D40 -> -8084.1336 | F40: =F39+E40 -> -4839.6307 | G40: =G39+F40 -> -1630.4058 | H40: =H39+G40 -> 1529.3334 | I40: =I39+H40 -> 4640.35 | J40: =J39+I40 -> 7703.3951 | K40: =K39+J40 -> 10719.209 | ... N40: =N39+M40 -> 19490.486
B43: Прогноз на 2030 год
B44: Дата | C44: 46023 | D44: 46054 | E44: 46082 | F44: 46113 | G44: 46143 | H44: 46174 | I44: 46204 | J44: 46235 | K44: 46266 | L44: 46296 | M44: 46327 | N44: 46357
B45: Net Profit | C45: ='P&L'!F105 -> 5780.8448 | D45: ='P&L'!G105 -> 5780.8448 | E45: ='P&L'!H105 -> 5780.8448 | F45: ='P&L'!I105 -> 5780.8448 | G45: ='P&L'!J105 -> 5780.8448 | H45: ='P&L'!K105 -> 5780.8448 | I45: ='P&L'!L105 -> 5780.8448 | J45: ='P&L'!M105 -> 5780.8448 | ... N45: ='P&L'!Q105 -> 5780.8448
B46: Амортизация | C46: =C33 -> 553.80754 | D46: =D33 -> 553.80754 | E46: =E33 -> 553.80754 | F46: =F33 -> 553.80754 | G46: =G33 -> 553.80754 | H46: =H33 -> 553.80754 | I46: =I33 -> 553.80754 | J46: =J33 -> 553.80754 | ... N46: =N33 -> 553.80754
B47: Общая выручка | C47: =SUM('P&L'!F90:F92) -> 25096.771 | D47: =SUM('P&L'!G90:G92) -> 25096.771 | E47: =SUM('P&L'!H90:H92) -> 25096.771 | F47: =SUM('P&L'!I90:I92) -> 25096.771 | G47: =SUM('P&L'!J90:J92) -> 25096.771 | H47: =SUM('P&L'!K90:K92) -> 25096.771 | I47: =SUM('P&L'!L90:L92) -> 25096.771 | J47: =SUM('P&L'!M90:M92) -> 25096.771 | ... N47: =SUM('P&L'!Q90:Q92) -> 25096.771
B48: ΔNWC | C48: =(C47-N34)*$R$4 -> 441.19863 | D48: =(D47-C47)*$R$4 -> 0 | E48: =(E47-D47)*$R$4 -> 0 | F48: =(F47-E47)*$R$4 -> 0 | G48: =(G47-F47)*$R$4 -> 0 | H48: =(H47-G47)*$R$4 -> 0 | I48: =(I47-H47)*$R$4 -> 0 | J48: =(J47-I47)*$R$4 -> 0 | K48: =(K47-J47)*$R$4 -> 0 | ... N48: =(N47-M47)*$R$4 -> 0
B49: FCFF | C49: =C45+C46-C48 -> 5893.4537 | D49: =D45+D46-D48 -> 6334.6524 | E49: =E45+E46-E48 -> 6334.6524 | F49: =F45+F46-F48 -> 6334.6524 | G49: =G45+G46-G48 -> 6334.6524 | H49: =H45+H46-H48 -> 6334.6524 | I49: =I45+I46-I48 -> 6334.6524 | J49: =J45+J46-J48 -> 6334.6524 | ... N49: =N45+N46-N48 -> 6334.6524
B50: Cumulative FCFF | C50: =N37+C49 -> 64837.541 | D50: =D49+C50 -> 71172.193 | E50: =E49+D50 -> 77506.845 | F50: =F49+E50 -> 83841.498 | G50: =G49+F50 -> 90176.15 | H50: =H49+G50 -> 96510.803 | I50: =I49+H50 -> 102845.45 | J50: =J49+I50 -> 109180.11 | K50: =K49+J50 -> 115514.76 | ... N50: =N49+M50 -> 134518.72
B51: Коэф. дисконтирования | C51: =$S$5^(COLUMN()+36-2) -> 1.7770926 | D51: =$S$5^(COLUMN()+36-2) -> 1.8049243 | E51: =$S$5^(COLUMN()+36-2) -> 1.8331918 | F51: =$S$5^(COLUMN()+36-2) -> 1.861902 | G51: =$S$5^(COLUMN()+36-2) -> 1.8910619 | H51: =$S$5^(COLUMN()+36-2) -> 1.9206785 | I51: =$S$5^(COLUMN()+36-2) -> 1.9507588 | J51: =$S$5^(COLUMN()+36-2) -> 1.9813103 | ... N51: =$S$5^(COLUMN()+36-2) -> 2.1083766
B52: DCF | C52: =C49/C51 -> 3316.3459 | D52: =D49/D51 -> 3509.65 | E52: =E49/E51 -> 3455.5317 | F52: =F49/F51 -> 3402.248 | G52: =G49/G51 -> 3349.7859 | H52: =H49/H51 -> 3298.1327 | I52: =I49/I51 -> 3247.276 | J52: =J49/J51 -> 3197.2035 | ... N52: =N49/N51 -> 3004.5165
B53: Cumulative DCF | C53: =N40+C52 -> 22806.832 | D53: =D52+C53 -> 26316.482 | E53: =E52+D53 -> 29772.014 | F53: =F52+E53 -> 33174.262 | G53: =G52+F53 -> 36524.047 | H53: =H52+G53 -> 39822.18 | I53: =I52+H53 -> 43069.456 | J53: =J52+I53 -> 46266.66 | K53: =K52+J53 -> 49414.563 | ... N53: =N52+M53 -> 58570.014
B55: Прогноз на 2031 год
B56: Дата | C56: 46023 | D56: 46054 | E56: 46082 | F56: 46113 | G56: 46143 | H56: 46174 | I56: 46204 | J56: 46235 | K56: 46266 | L56: 46296 | M56: 46327 | N56: 46357
B57: Net Profit | C57: ='P&L'!F131 -> 5477.7539 | D57: ='P&L'!G131 -> 5477.7539 | E57: ='P&L'!H131 -> 5477.7539 | F57: ='P&L'!I131 -> 5477.7539 | G57: ='P&L'!J131 -> 5477.7539 | H57: ='P&L'!K131 -> 5477.7539 | I57: ='P&L'!L131 -> 5477.7539 | J57: ='P&L'!M131 -> 5477.7539 | ... N57: ='P&L'!Q131 -> 5477.7539
B58: Амортизация | C58: =C46 -> 553.80754 | D58: =D46 -> 553.80754 | E58: =E46 -> 553.80754 | F58: =F46 -> 553.80754 | G58: =G46 -> 553.80754 | H58: =H46 -> 553.80754 | I58: =I46 -> 553.80754 | J58: =J46 -> 553.80754 | ... N58: =N46 -> 553.80754
B59: Общая выручка | C59: =SUM('P&L'!F116:F118) -> 25096.771 | D59: =SUM('P&L'!G116:G118) -> 25096.771 | E59: =SUM('P&L'!H116:H118) -> 25096.771 | F59: =SUM('P&L'!I116:I118) -> 25096.771 | G59: =SUM('P&L'!J116:J118) -> 25096.771 | H59: =SUM('P&L'!K116:K118) -> 25096.771 | I59: =SUM('P&L'!L116:L118) -> 25096.771 | J59: =SUM('P&L'!M116:M118) -> 25096.771 | ... N59: =SUM('P&L'!Q116:Q118) -> 25096.771
B60: ΔNWC | C60: 0 | D60: =(D59-C59)*$R$4 -> 0 | E60: =(E59-D59)*$R$4 -> 0 | F60: =(F59-E59)*$R$4 -> 0 | G60: =(G59-F59)*$R$4 -> 0 | H60: =(H59-G59)*$R$4 -> 0 | I60: =(I59-H59)*$R$4 -> 0 | J60: =(J59-I59)*$R$4 -> 0 | K60: =(K59-J59)*$R$4 -> 0 | ... N60: =(N59-M59)*$R$4 -> 0
B61: FCFF | C61: =C57+C58-C60 -> 6031.5614 | D61: =D57+D58-D60 -> 6031.5614 | E61: =E57+E58-E60 -> 6031.5614 | F61: =F57+F58-F60 -> 6031.5614 | G61: =G57+G58-G60 -> 6031.5614 | H61: =H57+H58-H60 -> 6031.5614 | I61: =I57+I58-I60 -> 6031.5614 | J61: =J57+J58-J60 -> 6031.5614 | ... N61: =N57+N58-N60 -> 6031.5614
B62: Cumulative FCFF | C62: =N50+C61 -> 140550.28 | D62: =D61+C62 -> 146581.84 | E62: =E61+D62 -> 152613.4 | F62: =F61+E62 -> 158644.96 | G62: =G61+F62 -> 164676.52 | H62: =H61+G62 -> 170708.09 | I62: =I61+H62 -> 176739.65 | J62: =J61+I62 -> 182771.21 | K62: =K61+J62 -> 188802.77 | ... N62: =N61+M62 -> 206897.45
B63: Коэф. дисконтирования | C63: =$S$5^(COLUMN()+48-2) -> 2.1413966 | D63: =$S$5^(COLUMN()+48-2) -> 2.1749337 | E63: =$S$5^(COLUMN()+48-2) -> 2.2089961 | F63: =$S$5^(COLUMN()+48-2) -> 2.2435919 | G63: =$S$5^(COLUMN()+48-2) -> 2.2787296 | H63: =$S$5^(COLUMN()+48-2) -> 2.3144175 | I63: =$S$5^(COLUMN()+48-2) -> 2.3506644 | J63: =$S$5^(COLUMN()+48-2) -> 2.387479 | ... N63: =$S$5^(COLUMN()+48-2) -> 2.5405938
B64: DCF | C64: =C61/C63 -> 2816.6485 | D64: =D61/D63 -> 2773.2162 | E64: =E61/E63 -> 2730.4536 | F64: =F61/F63 -> 2688.3505 | G64: =G61/G63 -> 2646.8965 | H64: =H61/H63 -> 2606.0818 | I64: =I61/I63 -> 2565.8964 | J64: =J61/J63 -> 2526.3307 | ... N64: =N61/N63 -> 2374.0755
B65: Cumulative DCF | C65: =N53+C64 -> 61386.662 | D65: =D64+C65 -> 64159.878 | E65: =E64+D65 -> 66890.332 | F65: =F64+E65 -> 69578.682 | G65: =G64+F65 -> 72225.579 | H65: =H64+G65 -> 74831.661 | I65: =I64+H65 -> 77397.557 | J65: =J64+I65 -> 79923.888 | K65: =K64+J65 -> 82411.263 | ... N65: =N64+M65 -> 89645.615
